[{"n":"书籍_CSDN会员免费电子书1000本_移动开发_深入解析Android 虚拟机.epub","i":"epub","s":660472,"p":"1411","l":"chinese","d":"https://url05.ctfile.com/f/64714105-1518436888-c63c6a?p=1411"},{"n":"书籍_CSDN会员免费电子书1000本_移动开发_深入理解Android内核设计思想（第2版）（上下册）.epub","i":"epub","s":1069703,"p":"1411","l":"chinese","d":"https://url05.ctfile.com/f/64714105-1518436885-93ade9?p=1411"},{"n":"书籍_CSDN会员免费电子书1000本_移动开发_深入浅出数据科学.epub","i":"epub","s":303973,"p":"1411","l":"chinese","d":"https://url05.ctfile.com/f/64714105-1518436873-20f8f2?p=1411"},{"n":"书籍_CSDN会员免费电子书1000本_移动开发_深入浅出Webpack.epub","i":"epub","s":1488667,"p":"1411","l":"chinese","d":"https://url05.ctfile.com/f/64714105-1518436870-fc003d?p=1411"},{"n":"书籍_CSDN会员免费电子书1000本_移动开发_树莓派开发实战（第2版）.epub","i":"epub","s":324966,"p":"1411","l":"chinese","d":"https://url05.ctfile.com/f/64714105-1518436864-2ee2f5?p=1411"},{"n":"书籍_CSDN会员免费电子书1000本_移动开发_构建跨平台APP：jQuery Mobile移动应用实战（第2版）.epub","i":"epub","s":423888,"p":"1411","l":"chinese","d":"https://url05.ctfile.com/f/64714105-1518436858-7e6eb1?p=1411"},{"n":"书籍_CSDN会员免费电子书1000本_移动开发_构建移动网站与APP：HTML 5移动开发入门与实战.epub","i":"epub","s":317566,"p":"1411","l":"chinese","d":"https://url05.ctfile.com/f/64714105-1518436852-b415f5?p=1411"},{"n":"书籍_CSDN会员免费电子书1000本_移动开发_极简Spring Cloud实战.epub","i":"epub","s":743023,"p":"1411","l":"chinese","d":"https://url05.ctfile.com/f/64714105-1518436849-4cd70d?p=1411"},{"n":"书籍_CSDN会员免费电子书1000本_移动开发_机器学习Web应用.epub","i":"epub","s":284045,"p":"1411","l":"chinese","d":"https://url05.ctfile.com/f/64714105-1518436837-d78730?p=1411"},{"n":"书籍_CSDN会员免费电子书1000本_移动开发_智能运维：从0搭建大规模分布式AIOps系统.epub","i":"epub","s":363546,"p":"1411","l":"chinese","d":"https://url05.ctfile.com/f/64714105-1518436834-35c268?p=1411"},{"n":"书籍_CSDN会员免费电子书1000本_移动开发_新经济崛起：阿里巴巴3万亿的商业逻辑.epub","i":"epub","s":604184,"p":"1411","l":"chinese","d":"https://url05.ctfile.com/f/64714105-1518436828-8f4944?p=1411"},{"n":"书籍_CSDN会员免费电子书1000本_移动开发_数据科学实战手册（第2版）.epub","i":"epub","s":303116,"p":"1411","l":"chinese","d":"https://url05.ctfile.com/f/64714105-1518436822-ec9470?p=1411"},{"n":"书籍_CSDN会员免费电子书1000本_移动开发_数据分析实战.epub","i":"epub","s":477599,"p":"1411","l":"chinese","d":"https://url05.ctfile.com/f/64714105-1518436810-6b6a33?p=1411"},{"n":"书籍_CSDN会员免费电子书1000本_移动开发_数据中心的网络互联结构和流量协同传输管理.epub","i":"epub","s":440699,"p":"1411","l":"chinese","d":"https://url05.ctfile.com/f/64714105-1518436807-4a966c?p=1411"},{"n":"书籍_CSDN会员免费电子书1000本_移动开发_数据中台：让数据用起来.epub","i":"epub","s":461805,"p":"1411","l":"chinese","d":"https://url05.ctfile.com/f/64714105-1518436801-8ebdf0?p=1411"},{"n":"书籍_CSDN会员免费电子书1000本_移动开发_数学与泛型编程：高效编程的奥秘.epub","i":"epub","s":668293,"p":"1411","l":"chinese","d":"https://url05.ctfile.com/f/64714105-1518436786-7848ac?p=1411"},{"n":"书籍_CSDN会员免费电子书1000本_移动开发_思维训练启蒙新观念：青少年Pascal语言编程抢先起跑一路通.epub","i":"epub","s":591147,"p":"1411","l":"chinese","d":"https://url05.ctfile.com/f/64714105-1518436777-847d92?p=1411"},{"n":"书籍_CSDN会员免费电子书1000本_移动开发_微软开源跨平台移动开发实践：利用ASP.NET Core 1.0 、Apache Cordova、Xamarin和Azure快速构建移动应用解决方案.epub","i":"epub","s":2075434,"p":"1411","l":"chinese","d":"https://url05.ctfile.com/f/64714105-1518436774-80e956?p=1411"},{"n":"书籍_CSDN会员免费电子书1000本_移动开发_微服务分布式构架开发实战.epub","i":"epub","s":213207,"p":"1411","l":"chinese","d":"https://url05.ctfile.com/f/64714105-1518436765-dfe13d?p=1411"},{"n":"书籍_CSDN会员免费电子书1000本_移动开发_微信营销与运营一册通.epub","i":"epub","s":295648,"p":"1411","l":"chinese","d":"https://url05.ctfile.com/f/64714105-1518436756-6791fd?p=1411"}]