[{"n":"104051、_russian_Методика обольщения_Габбер Холли_.fb2__pilimi-zlib-0-119999","i":"fb2","s":237702,"p":"8078","l":"russian","d":"https://url03.ctfile.com/f/64369603-1509249466-a3eada?p=8078"},{"n":"104052、_russian_Пока муж в командировке_Тихонова Карина_.fb2__pilimi-zlib-0-119999","i":"fb2","s":213413,"p":"8078","l":"russian","d":"https://url03.ctfile.com/f/64369603-1509249469-506c7b?p=8078"},{"n":"104053、_russian_Оловянные кольца_Габбе Тамара Григорьевна_.fb2__pilimi-zlib-0-119999","i":"fb2","s":53850,"p":"8078","l":"russian","d":"https://url03.ctfile.com/f/64369603-1509249472-1a494f?p=8078"},{"n":"104054、_russian_Город мастеров (вариант)_Габбе Тамара Григорьевна_.fb2__pilimi-zlib-0-119999","i":"fb2","s":25728,"p":"8078","l":"russian","d":"https://url03.ctfile.com/f/64369603-1509249475-b476fd?p=8078"},{"n":"104055、_russian_Город мастеров или Сказка о двух горбунах_Габбе Тамара Григорьевна_.fb2__pilimi-zlib-0-119999","i":"fb2","s":51374,"p":"8078","l":"russian","d":"https://url03.ctfile.com/f/64369603-1509249478-406f0e?p=8078"},{"n":"104056、_russian_Дрессировка и натаска охотничьих собак_Оберлендер Г._.fb2__pilimi-zlib-0-119999","i":"fb2","s":512266,"p":"8078","l":"russian","d":"https://url03.ctfile.com/f/64369603-1509249481-379fcd?p=8078"},{"n":"104057、_russian_Учитесь сами делать мебель_Клятис Г. Я._.fb2__pilimi-zlib-0-119999","i":"fb2","s":449539,"p":"8078","l":"russian","d":"https://url03.ctfile.com/f/64369603-1509249484-6d4048?p=8078"},{"n":"104058、_russian_Непрозрачная отделка самодельной кухонной мебели_Клятис Г. Я._.fb2__pilimi-zlib-0-119999","i":"fb2","s":39667,"p":"8078","l":"russian","d":"https://url03.ctfile.com/f/64369603-1509249487-3dcde7?p=8078"},{"n":"104059、_russian_Чеканка басма насечка_Федотов Г. Я._.fb2__pilimi-zlib-0-119999","i":"fb2","s":988005,"p":"8078","l":"russian","d":"https://url03.ctfile.com/f/64369603-1509249490-cfa5c2?p=8078"},{"n":"10405、_russian_Гроза из преисподней (Досье Дрездена - 1)_Батчер Джим_.fb2__pilimi-zlib-0-119999","i":"fb2","s":207761,"p":"8078","l":"russian","d":"https://url03.ctfile.com/f/64369603-1509249493-97273c?p=8078"},{"n":"104060、_russian_Справочник. Дрессировка собак_Крузеpман Г. В._.fb2__pilimi-zlib-0-119999","i":"fb2","s":72582,"p":"8078","l":"russian","d":"https://url03.ctfile.com/f/64369603-1509249496-04c468?p=8078"},{"n":"104061、_russian_Бурка_Тарбаев Г._.fb2__pilimi-zlib-0-119999","i":"fb2","s":53809,"p":"8078","l":"russian","d":"https://url03.ctfile.com/f/64369603-1509249499-57a9cf?p=8078"},{"n":"104062、_russian_ТАЙНЫ РУССКОЙ РЕВОЛЮЦИИ И БУДУЩЕЕ РОССИИ__.fb2__pilimi-zlib-0-119999","i":"fb2","s":734888,"p":"8078","l":"russian","d":"https://url03.ctfile.com/f/64369603-1509249502-d46293?p=8078"},{"n":"104063、_russian_Сингомэйкеры_Никитин Юрий Александрович_.fb2__pilimi-zlib-0-119999","i":"fb2","s":478496,"p":"8078","l":"russian","d":"https://url03.ctfile.com/f/64369603-1509249505-fe6be8?p=8078"},{"n":"104064、_russian_Курс Энциклопедии оккультизма_Г О М_.fb2__pilimi-zlib-0-119999","i":"fb2","s":357699,"p":"8078","l":"russian","d":"https://url03.ctfile.com/f/64369603-1509249508-fd91ce?p=8078"},{"n":"104065、_russian_Из рецептов старинной кухни_Тинькова Г. Н._.fb2__pilimi-zlib-0-119999","i":"fb2","s":15331,"p":"8078","l":"russian","d":"https://url03.ctfile.com/f/64369603-1509249511-161659?p=8078"},{"n":"104066、_russian_Как упорядочить свой внутренний мир_Макдональд Г._.fb2__pilimi-zlib-0-119999","i":"fb2","s":129051,"p":"8078","l":"russian","d":"https://url03.ctfile.com/f/64369603-1509249514-419cf1?p=8078"},{"n":"104067、_russian_Из глубины веков и вод_Линде_ Бреттшнейдер Г. Бреттшнейдер Э_.fb2__pilimi-zlib-0-119999","i":"fb2","s":238356,"p":"8078","l":"russian","d":"https://url03.ctfile.com/f/64369603-1509249517-82f4aa?p=8078"},{"n":"104068、_russian_Боснийский дневник_Г Игорь_.fb2__pilimi-zlib-0-119999","i":"fb2","s":19433,"p":"8078","l":"russian","d":"https://url03.ctfile.com/f/64369603-1509249520-d1a15f?p=8078"},{"n":"104069、_russian_Каменщик_Айдинов Г._.fb2__pilimi-zlib-0-119999","i":"fb2","s":203573,"p":"8078","l":"russian","d":"https://url03.ctfile.com/f/64369603-1509249523-a67350?p=8078"}]