[{"n":"_pilimi-zlib-0-119999_31975、_russian_Черная книга времен_Влодавец Леонид_.fb2","i":"fb2","s":153552,"p":"8078","l":"russian","d":"https://url03.ctfile.com/f/64369603-1509415222-024d63?p=8078"},{"n":"_pilimi-zlib-0-119999_31976、_russian_Клад под могильной плитой_Влодавец Леонид_.fb2","i":"fb2","s":143309,"p":"8078","l":"russian","d":"https://url03.ctfile.com/f/64369603-1509415225-089e3d?p=8078"},{"n":"_pilimi-zlib-0-119999_31977、_russian_В день смерти Его_Хласко Марек_.fb2","i":"fb2","s":36752,"p":"8078","l":"russian","d":"https://url03.ctfile.com/f/64369603-1509415234-f140e3?p=8078"},{"n":"_pilimi-zlib-0-119999_31978、_russian_Путь к богатству или Где зарыты сокровища_Синельников Валерий Владимирович_.fb2","i":"fb2","s":338992,"p":"8078","l":"russian","d":"https://url03.ctfile.com/f/64369603-1509415237-e4b1ec?p=8078"},{"n":"_pilimi-zlib-0-119999_31979、_russian_Терской Фронт_Громов Борис_.fb2","i":"fb2","s":447694,"p":"8078","l":"russian","d":"https://url03.ctfile.com/f/64369603-1509415246-db5f16?p=8078"},{"n":"_pilimi-zlib-0-119999_3197、_russian_Все возможно_Бузиновский Сергей_.fb2","i":"fb2","s":78044,"p":"8078","l":"russian","d":"https://url03.ctfile.com/f/64369603-1509415249-7ec271?p=8078"},{"n":"_pilimi-zlib-0-119999_31980、_russian_Праотец Мосох_Пензев Константин Александрович_.fb2","i":"fb2","s":321072,"p":"8078","l":"russian","d":"https://url03.ctfile.com/f/64369603-1509415252-775d7f?p=8078"},{"n":"_pilimi-zlib-0-119999_31981、_russian_Ваш беспокойный подросток. Практическое руководство для отчаявшихся родителей__.fb2","i":"fb2","s":188947,"p":"8078","l":"russian","d":"https://url03.ctfile.com/f/64369603-1509415258-b097dd?p=8078"},{"n":"_pilimi-zlib-0-119999_31982、_russian_Шанхай. Книга 1. Предсказание императора_Ротенберг Дэвид_.fb2","i":"fb2","s":447158,"p":"8078","l":"russian","d":"https://url03.ctfile.com/f/64369603-1509415261-225d6b?p=8078"},{"n":"_pilimi-zlib-0-119999_31983、_russian_Девятый круг_Белл Алекс_.fb2","i":"fb2","s":381827,"p":"8078","l":"russian","d":"https://url03.ctfile.com/f/64369603-1509415264-702d95?p=8078"},{"n":"_pilimi-zlib-0-119999_31984、_russian_Секреты бабушки Ванги_Калинина Дарья Александровна_.fb2","i":"fb2","s":287689,"p":"8078","l":"russian","d":"https://url03.ctfile.com/f/64369603-1509415267-f15db5?p=8078"},{"n":"_pilimi-zlib-0-119999_31985、_russian_Большая игра_Гулев Димитр_.fb2","i":"fb2","s":595189,"p":"8078","l":"russian","d":"https://url03.ctfile.com/f/64369603-1509415276-4773cd?p=8078"},{"n":"_pilimi-zlib-0-119999_31986、_russian_Когда соблазняет женщина_Калинина Дарья Александровна_.fb2","i":"fb2","s":307848,"p":"8078","l":"russian","d":"https://url03.ctfile.com/f/64369603-1509415279-a2ce9a?p=8078"},{"n":"_pilimi-zlib-0-119999_31987、_english_Heavens Spite_Saintcrow Lilith_.fb2","i":"fb2","s":203205,"p":"8078","l":"english","d":"https://url03.ctfile.com/f/64369603-1509415282-e41637?p=8078"},{"n":"_pilimi-zlib-0-119999_31988、_english_Total Recall_Anthony Piers_.fb2","i":"fb2","s":182515,"p":"8078","l":"english","d":"https://url03.ctfile.com/f/64369603-1509415288-06bc0d?p=8078"},{"n":"_pilimi-zlib-0-119999_31989、_russian_Из дневников_Жеромский Стефан_.fb2","i":"fb2","s":84606,"p":"8078","l":"russian","d":"https://url03.ctfile.com/f/64369603-1509415291-d80e45?p=8078"},{"n":"_pilimi-zlib-0-119999_3198、_russian_Тайна Воланда (фрагмент)_Бузиновский Сергей Бузиновская Ольга_.fb2","i":"fb2","s":59635,"p":"8078","l":"russian","d":"https://url03.ctfile.com/f/64369603-1509415294-fcf8b4?p=8078"},{"n":"_pilimi-zlib-0-119999_31990、_russian_ИЛЛЮСТРИРОВАННАЯ БИБЛИЯ_Библия_.fb2","i":"fb2","s":4304323,"p":"8078","l":"russian","d":"https://url03.ctfile.com/f/64369603-1509415300-80020d?p=8078"},{"n":"_pilimi-zlib-0-119999_31991、_russian_Штурмовые отряды (СА) Гитлера. 1921–1945_Литтлджон Д._.fb2","i":"fb2","s":2072072,"p":"8078","l":"russian","d":"https://url03.ctfile.com/f/64369603-1509415306-fdcbf4?p=8078"},{"n":"_pilimi-zlib-0-119999_31992、_russian_Большая река_Антонов Евгений_.fb2","i":"fb2","s":16428,"p":"8078","l":"russian","d":"https://url03.ctfile.com/f/64369603-1509415309-b9ed7c?p=8078"}]