{"024刘":"/ScAAA==","09章":"w0YAAA==","0版第一":"fkEAAA==","13丛":"hk0AABgQAQA=","13室":"aiQAAA==","1个重要":"BzMAAAkzAAAKMwAA","1六安兵":"ih8AAA==","1黄帝内":"XEgAANgFAQA=","208反":"qx8AAA==","20佘":"nx8AAA==","27天":"Cj4AAA==","2疡病大":"kUgAAHEGAQA=","2血泪的":"NQsAAA==","335双":"MRcAAA==","39专":"jB8AAA==","46孟":"JhcAAA==","56大":"RQsAAA==","5文王渭":"JxcAAA==","6带响的":"xCQAAA==","92大":"Vx8AAA==","ai工具最终给你们推":"5AsAAA==","atia环境中的设计cae及应用":"IyQAAA==","b编":"fxQAAA==","d室":"UCQAAA==","hypers":"zR4AAA==","k大":"BhUAAA==","linux编程":"AUcAAA==","nventor2定制与二次开发":"ixQAAA==","p实现网站站内静态页搜索引":"hUcAAA==","rch2014建筑":"USQAAA==","s6中文版入门与提高实例教程":"hRQAAA==","s迁":"8UYAAA==","theory":"K5MAAA==","x域":"dToAAA==","一八年":"xCcAAA==","一生要读知的100处世界著名建":"mgMBAA==","七案件":"QwsAAA==","七绝三":"BUgAABsFAQA=","三书评":"IUwAAIYNAQA=","上最强":"KTQAAPo0AAA=","不平均":"AkYAAA==","与间谍":"QYwAAA==","专利下载软件的原理与应用":"k0cAAA==","世界中":"VzoAAA==","业兵法":"dCQAAA==","业服务化案":"biQAAA==","东画报":"TzQAAFY0AAAdNQAAdDUAACU0AAA=","两如何":"Kk4AAIQRAQA=","中华帝":"uCcAAAiTAAA=","中国计算机软件专业技":"q0UAAKfaAACo2gAAgkEAAKlFAACqRQAA","中国道":"FzsAAA==","中央文":"pkAAAHZFAAB7hgAAfIYAAKJAAACjQAAApUAAAKFAAACkQAAA","中文版室内":"YyQAAA==","中止症":"sYsAAA==","中的攻":"tQAAAA==","临床力":"sjgAAA==","临床月":"4gsBAEhLAAA=","乾隆七":"vdoAAL7aAAC/2gAAwNoAAA==","事件的":"6ZIAAA==","事经济":"vTUAAA==","五规划教材":"CEIAAPlHAAAjSAAA6EgAABEFAQCfBQEAKgcBAA==","京话的":"UTQAAA==","人力资":"ZxQAAPgeAACZJAAA","人物原":"+EEAAIdCAACIRgAA","人看到":"4EAAAA==","什麼會":"gpIAAIOSAABaQAAA","今名医奇病":"JE4AAH0RAQA=","从阿穆":"YTQAAA==","代史研":"DzQAAHU5AADrOwAA","仿真和":"RxQAAA==","众丑外":"ajkAAA==","伯承军":"CToAAA==","位大师":"dQcAAA==","作俑者透视":"PwcAAA==","作基础":"nDMAALuSAAA=","健身食":"WU0AAOoPAQA=","先生应用附子的学术渊源与临床":"yUkAANQIAQA=","入学机":"UZAAAA==","全世界聪明":"/zQAAA==","全书本":"udoAAA==","关系领":"5DkAAA==","养猪你":"WRUAAHQVAAA=","军事冲突如":"QzsAAA==","农医论":"kUwAAFcOAQA=","分析从入门":"pycAAJ0nAACfJwAAqCcAALAnAAADFgAABBYAAMkeAADWHgAA1x4AAKMnAAA=","刘志远":"njIAAA==","判文献资料":"NjoAAA==","利范先生将7":"hoYAAA==","到的便":"MjMAAA==","制x":"MTYAAA==","制度研":"ORUAAA==","务员的鲁迅":"nz4AAA==","务网络":"IBQAAA==","劳埃德":"54YAAA==","勒律治":"2osAAA==","包头市1":"fkIAAMlOAADtEgEA","化操作全案":"9BUAAI8kAAA=","医科学":"fEEAAA==","千年的节食":"pDwAAA==","华出品d":"6gsAAOsLAADsCwAA","南京大":"KY4AACqOAAArjgAAzzMAAAs0AAAHQQAA","南省老中医":"shABAOlJAAC9TQAA8ggBAA==","印研究":"8TQAAA==","卷本新":"YD4AAA==","厘正按摩要":"fkgAAPoFAQA=","及实践":"/zMAAA==","发达风":"YU4AAB4SAQA=","古代卷":"L04AAIYRAQCHEQEAiBEBAC1OAAAuTgAA","古巴共":"0DwAAA==","合防治":"bhUAAA==","名演说":"CDcAAA==","含考研真题":"5toAAMcAAADIAAAAyQAAAFhEAABZRAAAZUQAAA==","吴大猷":"ATkAAAI5AAADOQAABDkAAAU5AAD/OAAAADkAAA==","员会出版发":"FIcAAA==","售攻心":"swAAALQAAAA=","四代秘":"30wAAAwPAQA=","国对基督教和天主教的政策":"Kz0AAA==","国最高法院大法官奥康纳和金斯伯格如何改变世":"JUAAAA==","国药典":"fkEAAH9BAACAQQAAkUIAAKhFAABTBwEAjkIAAI9CAACQQgAAD0kAAA==","地方关":"Iz8AAA==","堂医论":"S04AAKURAQA=","备手册第3版":"pxUAAA==","复正辑":"oUgAAIEGAQA=","大规模锂离子电池管理系统":"OhQAAA==","大马会致邱占萱等同学的一封信":"bjoAAA==","套装共7":"sDYAAA==","奥斯特":"jzIAAI0yAAA=","妇科儿科分":"yEgAAKYGAQA=","子领导":"8RUAAA==","字母学":"yoUAAA==","字经济":"lRcAAA==","孙岱君":"6DEAAA==","孙秉严":"YQsBAGILAQApSwAAKksAACtLAABfCwEA","学习型":"AB8AAPs0AAA=","学出现":"2jcAAA==","宁财经":"MJAAAA==","宁选集第一":"QDkAAA==","宋史第":"UlQAAFNUAABXVAAAVVQAAE1UAABOVAAAT1QAAFBUAABRVAAAVFQAAFpUAABZVAAAVlQAAFhUAABLVAAATFQAAA==","完全读":"2QkBAGtKAAA=","宏编译":"NoYAAA==","宝书著":"uNoAAA==","实战案例版":"qBQAAKkUAACqFAAAqxQAAKwUAAA=","实现sql数据库模":"u0UAAA==","实践成":"pIUAAA==","容店金":"pBYAAA==","尋求歷":"KkEAAA==","小组编":"PToAAA==","尔曼等":"roYAAK+GAAA=","尿酸血":"PE4AAJcRAQA=","展的影":"BTgAAA==","峰医案":"9EoAAPVKAAC+SwAA5UsAAC0LAQAuCwEAuAwBAOYMAQA=","州名老中医学术思想及医疗经验选编":"VkoAAMUJAQA=","工作的":"oCQAANyKAAA=","工科用":"VzUAAFg1AABZNQAA","左季云证治实验录199":"okcAAFUEAQA=","希尔经":"TzYAAA==","年妇科":"7EoAACQLAQA=","幸次郎":"yDsAAA==","应用从":"WhQAAGEUAAA=","庭与办":"XhQAAGgUAABqFAAAVhQAAFgUAABZFAAAZhQAAFcUAABcFAAAXxQAAGIUAABjFAAAZBQAAGUUAABrFAAAWxQAAGAUAABhFAAAZxQAAGkUAABsFAAAbRQAAG4UAABaFAAAXRQAAA==","开放与":"FToAAEpBAAA=","式经典":"rkUAAA==","张胜波":"AIgAAA==","张齐明":"IDQAAA==","弥留之":"AIYAAA==","录13":"KzQAAA==","彼特里":"SzoAAA==","往东来":"TToAAA==","得期待":"sjgAAA==","心理学原理":"xDcAAA==","志一医":"TwoBAHxKAAA=","念乐理":"00UAAA==","慎微编":"XUEAAF5BAAA=","懂中美贸易战中的美国内部逻辑":"uTcAAA==","成为专":"qCQAAA==","我国跨":"GkAAAA==","手把手教你如何实施与维持5s":"CxYAAA==","技术文献出":"GjUAAA==","拉伯帝":"qDUAAA==","拉基米":"f4YAALiKAAA=","持5s":"CxYAAA==","指迷新":"hUwAAEwOAQA=","改革开":"SkEAAA==","效栽培":"3hYAANUWAADYFgAA0RYAANIWAAC/FgAAwRYAAMUWAADrFgAAzBYAAM4WAADUFgAA3xYAAOAWAADkFgAA7RYAAMgWAADJFgAA2RYAAOIWAADoFgAAyhYAAOMWAADHFgAAzxYAANMWAADLFgAA1hYAANcWAADhFgAA7xYAAMIWAADbFgAA","教会更":"3I0AAA==","教学丛":"UjUAAFM1AAA=","斯商人":"cR8AAA==","斯迈特":"2QsAAA==","新科学":"8x4AAA==","新认识":"hjcAAKSFAAAFhgAA","新趋势":"ojYAAA==","方修道":"awoBAJVKAAA=","施一本":"rSQAAA==","施略特":"Pj0AAA==","日本防":"stgAAMc+AADIPgAAsdgAAA==","旧石器":"tjwAAA==","明景泰":"wdoAAA==","明末清初的":"ZjwAAA==","易外治":"HEgAADIFAQAzBQEAG0gAAA==","易水待":"Aj8AAA==","時報出版公":"jjcAANY3AAA=","景全书":"PkwAAKENAQA=","有效执行五":"9RUAAA==","术精萃":"UUwAALYNAQA=","机和信":"XkAAAA==","权主义":"/TwAAA==","李知宴":"NTQAAA==","村生活":"aDkAAA==","林则徐禁烟":"2ScAANonAAA=","林大学":"3TMAAA==","林日记":"BTYAAA==","校雠学":"4IoAAA==","根茎药材分":"C0kAAE8HAQA=","格上研":"IYYAAA==","格少将":"VTQAAA==","步琪咳":"FUsAABZLAABOCwEATwsBAA==","毒般传":"vTUAAA==","氏孤儿":"qh8AAMwBAQDTAQEA","江省中":"tEkAAL8IAQA=","污染防":"cxUAAA==","汤剂治疗慢性非特异性结肠炎25例":"1EoAABcLAQA=","河北大":"LDUAAA==","治的艺":"CJMAAA==","法全书":"4AEBAA==","法在高":"lz0AAA==","法系司法鉴定制度的观察与":"aDwAAA==","注环周":"yUoAAMpKAACeCgEAnwoBAA==","洲王室":"V9cAAA==","海上擒":"VwsAAA==","温五脏之阳善用益之滥用误之─":"TU4AAKcRAQA=","灸甲乙":"2kgAALnaAAC3BgEA","然哲学":"gTcAAA==","王国的覆灭":"TBcAAA==","王尔德":"vYYAAA==","珠宝曼":"bRYAAA==","球更佳":"LBQAAA==","理性与启蒙":"iI8AAA==","理性的神奇力量":"9/0AAEwDAQA=","生产与服务的信息系统与信":"6hUAAA==","生白医":"4ksAAOMMAQA=","由转向":"i4YAAA==","电动机":"BocAAA==","电子表":"YhQAAG4UAAA=","电脑维":"dBQAAHYUAAA=","画生命":"6zQAAA==","界地理大发":"HTUAAA==","疗男女":"VksAAPILAQA=","病学讲":"Wg4BANlKAADaSgAAlEwAAE0EAQAdCwEAIQsBAA==","痘科辨":"mU0AAI8QAQA=","登回忆":"TjsAAA==","的工作":"1oUAAA==","的干法":"lxcAAA==","的机制分析":"UZAAAA==","的民主":"vEAAAA==","的源流及其与痹病关系历史文献复习":"RE0AAO0PAQA=","的贪婪":"PwcAAA==","的黑社":"+zUAAA==","皇汉医学丛书08伤风约言":"oE0AAJYQAQA=","眼科现":"8kcAAAcFAQA=","知三联出版":"joYAAI+GAAA=","研英语":"ikIAAIxCAADfRgAAjEcAANk1AABoQgAAiUIAAJ1CAACLRwAAjUcAAI9HAADUAAAAiEIAAA==","科学高":"v0oAAJMKAQA=","程第二":"0o0AAA==","稿可搜":"/EoAAEkLAQA=","笔字帖":"CjQAAA==","第四卷":"kDcAAEE5AADvTAAAGg8BAGAXAAAAMwAA","等教育出版":"yzMAAF00AAC3OQAAuTkAAMk5AABlOgAAcDcAAMg5AAD6PAAAeUAAAGGGAABihgAA+DQAALg5AAA/OgAA1z0AAD44AAA9OgAAo5IAAA==","答s":"q0EAACdGAAA=","答与实":"XBUAAA==","算机控":"Bz0AAA==","算机等级考试命题研究中心":"kUcAAJJCAAA=","精通比":"g0YAAA==","糖橘高":"yhYAAA==","级文学":"hDwAAA==","线无战":"84UAAA==","经典大":"VxYAAFgWAAA=","经典跑":"EhUAAA==","绘精选":"IzYAAA==","统大全":"pgUBAKcFAQAqSAAAK0gAAA==","统架构":"w0EAANJBAABDRgAAUkYAAA==","续创新":"QR8AAA==","维亚克":"pIYAAKWGAAA=","维坦的":"DzoAAA==","编20":"ZE4AACESAQA=","编程大":"2jUAAFaIAAA=","罗科特":"wQIBAA==","羅汝芳":"bjQAAG80AAA=","羊实用":"ghUAAA==","美河提":"bEYAAA==","美第奇":"qDIAAA==","能制氢":"NhQAAA==","脑血管病医":"3toAAA==","舫临证":"AEsAADcLAQA=","良夫专":"l04AAFcSAQA=","花落知":"lQoAAA==","莱尔美":"/j0AAA==","落知多":"lQoAAA==","蒙古人":"UjQAAA==","薛氏医案选":"j0oAAGIKAQA=","藏海花":"ajoAAA==","藏经语":"qwUBAC9IAAA=","装共10册":"rDYAAA==","西田几":"0DcAAM2KAAA=","解读量":"po8AAA==","识自己":"VIYAAA==","词随身":"SCoAAA==","试最常":"pCQAAA==","课教程":"PDUAAA==","谈方法":"LpAAAA==","谷创新":"KRYAAA==","谷子全":"rUYAAA==","象级畅":"lhcAAA==","财富增":"UjYAAA==","资料对":"S9cAAA==","赞无数":"rhcAAA==","超级蓝":"IYYAAA==","超麟回":"sYUAAA==","趋势技术分":"0YYAAA==","软与极":"4EUAAA==","迈尔斯":"TzYAAJeGAAA=","运营模":"TxQAAA==","造业巨":"Sx8AAA==","量寿经":"sjsAAA==","钦安及其著":"nUkAAEMIAQA=","锡思考力系":"yi4AAA==","锡武医":"tkkAAMEIAQA=","键影响":"R9cAAA==","长安与":"g4sAAA==","门与实":"8BQAAJcnAABkFAAAZhQAAGcUAAA=","问题解":"WTUAAKonAABXNQAAWDUAAA==","间谍档":"PDQAAA==","闹衙门":"TP4AANMAAQA=","队伍的1":"6xUAAA==","阿兹布":"eRcAAHoXAAA=","陈景河":"j0kAADcIAQA=","集第九":"WDwAAA==","需要大战略":"CzcAAA==","霍夫曼":"FTQAAA==","面复辟":"ozwAAA==","革命献":"cQsAAA==","顽童的":"Bj4AAA==","领导团":"3TYAAA==","高岗在":"I4cAAA==","高级预":"swEBAA==","鼻喉科":"80gAACJJAABBTgAAswYBADQHAQBmBwEAnREBANZIAAA="}