{"05金匮354页d":"egsAAGcDAQA=","2黄帝内经素问注证发":"+QcAAA==","全国中医药行业高等":"iwcAALUHAAB4CAAAm/wAAHMDAQCHAwEAigMBAA==","全国高等中医药院校":"tQcAAHgIAACb/AAAcwMBAIcDAQCKAwEAiwcAAA==","功因素与临床情况的调查":"KQ0AAA==","咳嗽之辨证论治":"MAcAAA==","四肢躯干皮肤病诊疗选方":"6AoAAA==","国柏林图书馆手抄郎中经":"TzUBAFA1AQA=","学pdf电子":"WwAAAFQGAAA=","宋鹭冰60年疑难杂":"5woAAA==","广西1962中":"3Q0AANj8AAAyNQEA","杜雨茂肾病临床经验及实":"SQ4AAA==","枢机的原理及其临床意义初探":"LwsAAKf8AAA=","氏三代家传骨伤":"Eg4AABMOAAA=","湖南中草药单方验方选编":"IzUBAJ0NAADJ/AAA","皇汉医学丛书02医":"kA0AAJENAAA=","美中老中医治疗老年":"fQkAAA==","记13024219":"BfkAAA==","近代中医流派经":"EQ0AAA==","阁影钞清陈世杰仿宋":"lzABAA==","附子超量也不中毒的秘密":"Pw4AAFb8AAA=","雨茂肾病临床经验及实验":"SQ4AAA=="}