[{"n":"75404、_russian_Попытка возврата - 3_Конюшевский Владислав Николаевич_.fb2__pilimi-zlib-0-119999","i":"fb2","s":217465,"p":"8078","l":"russian","d":"https://url03.ctfile.com/f/64369603-1510107295-5d3a99?p=8078"},{"n":"75405、_russian_Газета К Барьеру! №23 от 27.10.2009_К барьеру! (запрещенная Дуэль)_.fb2__pilimi-zlib-0-119999","i":"fb2","s":400328,"p":"8078","l":"russian","d":"https://url03.ctfile.com/f/64369603-1510107298-7f138b?p=8078"},{"n":"75406、_russian_Газета К Барьеру! №23 от 27.10.2009_К барьеру! (запрещенная Дуэль)_.fb2__pilimi-zlib-0-119999","i":"fb2","s":400378,"p":"8078","l":"russian","d":"https://url03.ctfile.com/f/64369603-1510107304-5d3570?p=8078"},{"n":"75407、_russian_Газета К Барьеру! №23 от 27.10.2009_К барьеру! (запрещенная Дуэль)_.fb2__pilimi-zlib-0-119999","i":"fb2","s":400372,"p":"8078","l":"russian","d":"https://url03.ctfile.com/f/64369603-1510107310-079fa5?p=8078"},{"n":"75408、_russian_Газета К Барьеру! №23 от 27.10.2009_К барьеру! (запрещенная Дуэль)_.fb2__pilimi-zlib-0-119999","i":"fb2","s":400313,"p":"8078","l":"russian","d":"https://url03.ctfile.com/f/64369603-1510107313-46c6d2?p=8078"},{"n":"75409、_russian_Лучший из лучших_Смит Уилбур_.fb2__pilimi-zlib-0-119999","i":"fb2","s":566279,"p":"8078","l":"russian","d":"https://url03.ctfile.com/f/64369603-1510107316-c20995?p=8078"},{"n":"7540、_russian_А вам бы это понравилось_Блок Лауренс_.fb2__pilimi-zlib-0-119999","i":"fb2","s":4820,"p":"8078","l":"russian","d":"https://url03.ctfile.com/f/64369603-1510107319-49c4ce?p=8078"},{"n":"75410、_russian_Взгляд тигра_Смит Уилбур_.fb2__pilimi-zlib-0-119999","i":"fb2","s":330616,"p":"8078","l":"russian","d":"https://url03.ctfile.com/f/64369603-1510107325-b8a1ff?p=8078"},{"n":"75411、_russian_Happy Life навсегда!_Прыткина Эмилия_.fb2__pilimi-zlib-0-119999","i":"fb2","s":226217,"p":"8078","l":"russian","d":"https://url03.ctfile.com/f/64369603-1510107331-ccf945?p=8078"},{"n":"75412、_russian_Зюзюка и другие_Вильмонт Екатерина Николаевна_.fb2__pilimi-zlib-0-119999","i":"fb2","s":226601,"p":"8078","l":"russian","d":"https://url03.ctfile.com/f/64369603-1510107334-c2bbca?p=8078"},{"n":"75413、_russian_Мадам одиночка или Укротительница мужчин_Шилова Юлия Витальевна_.fb2__pilimi-zlib-0-119999","i":"fb2","s":299019,"p":"8078","l":"russian","d":"https://url03.ctfile.com/f/64369603-1510107337-b99d42?p=8078"},{"n":"75414、_russian_Что может быть проще времени_Саймак Клиффорд Д._.fb2__pilimi-zlib-0-119999","i":"fb2","s":182555,"p":"8078","l":"russian","d":"https://url03.ctfile.com/f/64369603-1510107343-4c5da8?p=8078"},{"n":"75415、_russian_Убийственная панацея_Саймак Клиффорд Дональд_.fb2__pilimi-zlib-0-119999","i":"fb2","s":14784,"p":"8078","l":"russian","d":"https://url03.ctfile.com/f/64369603-1510107346-d55251?p=8078"},{"n":"75416、_russian_Кладбище для безумцев_Брэдбери Рэй_.fb2__pilimi-zlib-0-119999","i":"fb2","s":372672,"p":"8078","l":"russian","d":"https://url03.ctfile.com/f/64369603-1510107349-4f82b9?p=8078"},{"n":"75417、_russian_Кроссвордист из преисподней_Каришнев-Лубоцкий Михаил Александрович_.fb2__pilimi-zlib-0-119999","i":"fb2","s":5280,"p":"8078","l":"russian","d":"https://url03.ctfile.com/f/64369603-1510107352-bd00c7?p=8078"},{"n":"75418、_russian_У жизни в лапах_Каришнев-Лубоцкий Михаил Александрович_.fb2__pilimi-zlib-0-119999","i":"fb2","s":7179,"p":"8078","l":"russian","d":"https://url03.ctfile.com/f/64369603-1510107355-301171?p=8078"},{"n":"75419、_russian_Найдите дедушку!_Каришнев-Лубоцкий Михаил Александрович_.fb2__pilimi-zlib-0-119999","i":"fb2","s":6233,"p":"8078","l":"russian","d":"https://url03.ctfile.com/f/64369603-1510107361-3ba0df?p=8078"},{"n":"7541、_russian_Возмездие_Блок Александр_.fb2__pilimi-zlib-0-119999","i":"fb2","s":27413,"p":"8078","l":"russian","d":"https://url03.ctfile.com/f/64369603-1510107364-5c3cf9?p=8078"},{"n":"75420、_russian_Застолье с барабашкой_Каришнев-Лубоцкий Михаил Александрович_.fb2__pilimi-zlib-0-119999","i":"fb2","s":6333,"p":"8078","l":"russian","d":"https://url03.ctfile.com/f/64369603-1510107367-22750b?p=8078"},{"n":"75421、_russian_Жертва искусства_Каришнев-Лубоцкий Михаил Александрович_.fb2__pilimi-zlib-0-119999","i":"fb2","s":5686,"p":"8078","l":"russian","d":"https://url03.ctfile.com/f/64369603-1510107373-4861fd?p=8078"}]