{"99":"q3IBAC93AQDicwEANncBAC55AQCscgEAuXMBAPp2AQBpeAEAq3kBALp5AQCicgEAsnMBAOtzAQCpcgEA","eyond音":"aXgBAA==","ond音乐特辑劲":"aXgBAA==","r":"6HgBAIp5AQC6eQEArX4BAA==","三季":"+nYBAPx2AQA=","之杯":"Rf0AAA==","乐园":"ae4AAG7uAAA=","名人":"XngBAA==","周年暨2013第四届会":"FnYBAAZ4AQATdgEA","夎湤":"pXIBAA==","届会":"E3YBABZ2AQAGeAEA","底深圳举行心内心外演唱":"N3kBAA==","开些":"b+8AAA==","录制":"yHMBAA==","心太":"zPwAAA==","捉迷":"PO8AAMv+AAA=","有什么东西渐渐地消失了":"l/gAAND4AAA=","枕难":"QvAAACzwAAA=","歌谣":"RCABAA==","相爱":"AvUAAA==","第四":"tnMBALtzAQATdgEAFnYBAAZ4AQA=","红热":"B3QBAAZ0AQA=","钰莹":"1CQBAA==","驹最后一次演唱海阔天空":"NncBAA==","鲜花":"8/QAAA=="}