{"0fd352a03585eda8d2d7de99ea2a3544":"ROMLAA==","1个重要问题的":"7+YLAA==","2285f0b85a68dbc5bd0a2e318b8d982c":"NugLAA==","2323d29b889fa6fb6cf7c024181befa1":"quYLAA==","2o死生":"neMLAA==","42ad41171bbd07d8932475ae77f9bbce":"d/cKAA==","4cf1a224f9de49fa323e046ed4c96f02":"ceULAA==","68年中":"VN8KAA==","92f648e75ba56d51721a0aeff82b1f4a":"XN8LAA==","b20a4f4b79ce6632bc0b271f79a6d29f":"7eYLAA==","b7f4173dc6314d1a6c9f47c58aeb5b42":"998LAA==","b9ce07b4bad06f6b9ee746752be56020":"XugLAA==","b函数速查手册":"EOILAA==","cc4dbf5341908cf88ca5b73621a14fb8":"a+kLAA==","d3c4a2f7142873b726b68a6e7ac9fab0":"veALAA==","id从入":"cuILAA==","itrix和mi":"0OELAA==","j布洛克曼":"WeULAA==","lp卓越":"GPkKAA==","python私房菜":"N+ELAA==","shark网络分析就":"y+ELAA==","一个实践者的":"hOMLAA==","不会讲故事的":"OuQLAA==","与公正的正面":"GOQLAA==","世界图书出版":"jeULAKDfCwBo4AsAMuQLAA==","世界经典科普":"H/cKAA==","世纪高等师范院校数学教育教学系":"oeULAA==","业的互联网机":"M+ULAA==","两届得主":"qLsLAA==","个中国父":"/uILAA==","个赞同认证的":"yucLAA==","中国历史上那":"eeYLAA==","中国断代":"MeYLAA==","中国童话":"GeoLAA==","中文版在港澳台和东南亚地区狂销12":"hd8LAA==","为什么精":"ZFELAFfpCwA=","主编钱乘":"n+YLAA==","之下的真实世":"YOQLAGHkCwA=","互联网必备图":"AOQLAA==","些事现在不做":"rugLAHPpCwA=","京工业大":"id8LAA==","人力资源新手":"QfcKAA==","人开展对":"EFILAA==","代法学家":"hfcKAO7gCwA=","优秀到卓越的行动":"6rsLAA==","优米网编":"P98KAA==","会简化工作的":"0OgLAA==","会美德与":"6OkLAA==","会讲故事和很":"w+cLAA==","会追随你":"SeQLAA==","俄罗斯的良心":"5N4LAA==","共情认知行为":"894LAA==","关于平庸":"0t4LAFf6CgA=","其深深触":"4d8LAA==","内部讲话系列":"UOQLAA==","再现三百年春秋最为恢弘奇谲之画":"aucLAA==","创业公司长演不衰的21种经典死":"ouMLAA==","创始人江南春":"d+MLAA==","刻地影响着每":"2OgLAA==","北洋军阀时代的奉":"juYLAA==","历史风云人物":"K98KAA==","史学家詹":"oOYLAA==","史料对照下的中国驻印军归国之战":"4uYLAA==","听都是一种艺":"/egLAA==","周刊精选必读":"aOMLAA==","哈尔滨出版社":"8d4LAArmCwA=","唐代藩镇研究":"6eYLAA==","国当代作":"qd8KALD3CgA=","国晚期的叛乱":"buYLAA==","国藩家书":"qeALAA==","在到2100":"fOILAA==","在港澳台":"hd8LAA==","基石丛书":"PuULAA==","大学出版社集":"8uYLAA==","大清帝國與中":"id4LAA==","天下书系":"cegLAA==","奖得主阿":"AN8LAA==","女不强大":"jvUKAOLnCwA=","学史上最经典":"rd4LAA==","学家的锅略大":"JuMLAA==","学建模竞":"oOULAA==","学校经典教材":"o/gKAJ7eCgA=","安然于行的幸":"D+kLAA==","导力21法则":"SeQLAA==","小松左京":"ct8LAA==","尼德霍夫":"G7sLAA==","建模竞赛":"oOULAA==","开餐巾纸":"qeMLAA==","弗洛伊德":"XPkKAP6VCwA=","当当网5星":"x94LAA==","微小的创新颠":"wuQLAA==","德国最高战功":"HOALABngCwAa4AsAG+ALAA==","战争经典系列":"u+YLANzmCwA=","所栖居世界的真相":"g+ULAA==","找寻真实的蒋":"yuALAA==","把手教你读财":"ouQLAA==","投资基金运作":"2uMLAA==","报畅销小说精":"WN8LAA==","政治生涯":"KN0KAA==","教材经典译丛":"oeQLAA==","数据库管理员指南":"BOILAA==","文化乐跑人生":"DOoLAA==","文化的精神與戰爭":"it4LAA==","新中产阶":"zukLAA==","时期的北平民":"HeALAA==","春树首次授权国内":"u94LAAPgCwAE4AsA","晚期的叛乱及其敌":"buYLAA==","最后的读书会":"AekLAA==","最权威的散文大系":"Dt8KAA==","有效的交互设":"PuELAA==","李朝朝鲜汉文燕行":"uuYLAA==","杜拉斯电子书":"N98LAA==","析mapreduce架构设计与":"R+ILAA==","林出版集团有限责":"H+kLACDpCwDf5wsA2egLABfpCwBT6QsAxuILABjpCwC74gsAvuILAPjiCwAi6QsAnekLABzpCwC/4gsAweILAMPiCwDN4gsA8+QLAHnnCwAa6QsAwOILAMLiCwAb6QsAxOILAMXiCwAd6QsAIekLABnpCwAe6QsA","架开发单页应":"ZeILAA==","械习练精":"AeoLAA==","民族抗日战争全史":"beYLAA==","民间药膳食疗防治病方1600例":"GuMLAA==","江南春等众多":"d+MLAA==","汴京之围":"1YgKAA==","法解释理解与适用":"4uALAA==","海财经大":"s+cLAA==","清并摆脱别人对你生活的隐性控制":"zx8QADw5EAA=","热锅上的家庭":"MDMQAFk5EAA=","然于行的幸福":"D+kLAA==","现企业成功转":"AOULAA==","珠楼主作":"/d4LAA==","理科学与工程":"l+MLAA==","用理工科思维":"VOkLAA==","男医生告诉你":"/+ALAADhCwA=","的微信帝国是如何建立起来的":"xeQLAA==","的心被这部小":"+t8LAA==","的思路拆解任":"FuQLAA==","的教父级经典":"5N8LAA==","的本多利范先生将7":"V7sLAA==","的本质在于如":"fecLAA==","着回来的男人":"vfgKAA==","研社科学出版":"qOULAA==","礼仪与沟":"5eQLAA==","社会科学院著名翻译家罗新璋权威":"2fgKAA==","福短篇悬念故":"6N4LAA==","种经穴按摩法":"COMLAA==","科幻经典烧脑":"jBELAA==","科思维理解世":"VOkLAA==","究生参考书系":"7eALAA==","窍门1200":"/OgLAA==","立铭科普力作":"hjcQAMk3EAA=","线程1基础":"JeILAA==","经典短篇作品":"EN0KAA==","维尼斯科":"4+ELAA==","聪明人的一张":"0N4LAA==","能错过的英语":"NeMLAA==","腾飞经典套装":"nOYLAA==","舟和她的天才同学":"Gt4KAA==","著小说系列畅":"hPUKAA==","被其深深":"4d8LAA==","被雨打风吹去":"t+YLAA==","複雜生命的起":"jVELAA==","西人民出":"/d8LAPzlCwAV5wsAZOcLAJXnCwAo6AsA9d4LALHiCwB73wsA","观与国际经济":"uOQLAA==","許家琳審":"et4LAA==","諾夫王朝的大":"hN4LAA==","让强迫症":"p+cLAA==","讲义大纲":"UOcLAA==","设计师考试全":"p0oKAMRlCgA=","诃夫小说全集":"a/cKAA==","译林幻系":"V98LAITfCwCf9woAHxILAA==","读书t":"HOgLAA==","贵州教育出版":"kucLAA==","走到哪里都能":"QuMLAA==","遍世界科幻大":"n/cKAA==","那一张旧书单":"1ugLAA==","里巴巴系":"IOULAA==","重新了解市场":"T+ALAA==","重新设计之道":"D+ELAA==","长安及各地人":"6uYLAA==","霍金毕生对黑":"Dd8LAA==","韩国电影":"Ot4KAA==","首部女性现实":"YzMQAA==","高战功勋章获得者":"GeALABrgCwAb4AsAHOALAA==","魄的人类文明":"St8LAA=="}