[{"n":"16793、_russian_Nebel_Ливадный Андрей_.fb2__pilimi-zlib-0-119999","i":"fb2","s":28337,"p":"8078","l":"russian","d":"https://url03.ctfile.com/f/64369603-1509339808-37cf67?p=8078"},{"n":"16794、_russian_Мятежный Процион_Ливадный Андрей Львович_.fb2__pilimi-zlib-0-119999","i":"fb2","s":293801,"p":"8078","l":"russian","d":"https://url03.ctfile.com/f/64369603-1509339817-179d42?p=8078"},{"n":"16795、_russian_Мишень_Ливадный Андрей_.fb2__pilimi-zlib-0-119999","i":"fb2","s":93679,"p":"8078","l":"russian","d":"https://url03.ctfile.com/f/64369603-1509339820-596221?p=8078"},{"n":"16796、_russian_Мишень_Ливадный Андрей_.fb2__pilimi-zlib-0-119999","i":"fb2","s":93659,"p":"8078","l":"russian","d":"https://url03.ctfile.com/f/64369603-1509339826-c3887d?p=8078"},{"n":"16797、_russian_Мир на ладони_Ливадный Андрей_.fb2__pilimi-zlib-0-119999","i":"fb2","s":38212,"p":"8078","l":"russian","d":"https://url03.ctfile.com/f/64369603-1509339829-b39f81?p=8078"},{"n":"16798、_russian_Лес_Ливадный Андрей_.fb2__pilimi-zlib-0-119999","i":"fb2","s":14228,"p":"8078","l":"russian","d":"https://url03.ctfile.com/f/64369603-1509339844-21fae8?p=8078"},{"n":"16799、_russian_Лес_Ливадный Андрей_.fb2__pilimi-zlib-0-119999","i":"fb2","s":13645,"p":"8078","l":"russian","d":"https://url03.ctfile.com/f/64369603-1509339850-118da0?p=8078"},{"n":"1679、_russian_Небо Одессы 1941-й_Череватенко Алексей Тихонович_.fb2__pilimi-zlib-0-119999","i":"fb2","s":123181,"p":"8078","l":"russian","d":"https://url03.ctfile.com/f/64369603-1509339859-64cdde?p=8078"},{"n":"167、_russian_Отчет о лечении зуба_Данченко Владимир (N20)_.fb2__pilimi-zlib-0-119999","i":"fb2","s":6841,"p":"8078","l":"russian","d":"https://url03.ctfile.com/f/64369603-1509339865-fc6e3d?p=8078"},{"n":"16800、_russian_Как убить золотого соловья_Стеклач Войтек_.fb2__pilimi-zlib-0-119999","i":"fb2","s":158770,"p":"8078","l":"russian","d":"https://url03.ctfile.com/f/64369603-1509339868-38a3a4?p=8078"},{"n":"16801、_russian_Лайбен по прозвищу Стикс_Ливадный Андрей_.fb2__pilimi-zlib-0-119999","i":"fb2","s":25329,"p":"8078","l":"russian","d":"https://url03.ctfile.com/f/64369603-1509339871-dd5791?p=8078"},{"n":"16802、_russian_Ксеноб-19_Ливадный Андрей Львович_.fb2__pilimi-zlib-0-119999","i":"fb2","s":260605,"p":"8078","l":"russian","d":"https://url03.ctfile.com/f/64369603-1509339880-af9b7c?p=8078"},{"n":"16803、_russian_Ковчег_Ливадный Андрей Львович_.fb2__pilimi-zlib-0-119999","i":"fb2","s":240378,"p":"8078","l":"russian","d":"https://url03.ctfile.com/f/64369603-1509339883-a2ff02?p=8078"},{"n":"16804、_russian_Холодное пламя Эригона_Ливадный Андрей_.fb2__pilimi-zlib-0-119999","i":"fb2","s":230339,"p":"8078","l":"russian","d":"https://url03.ctfile.com/f/64369603-1509339892-f3dca2?p=8078"},{"n":"16806、_russian_Город мертвых_Ливадный Андрей_.fb2__pilimi-zlib-0-119999","i":"fb2","s":26758,"p":"8078","l":"russian","d":"https://url03.ctfile.com/f/64369603-1509339904-d8a677?p=8078"},{"n":"16807、_russian_Форт Стеллар_Ливадный Андрей Львович_.fb2__pilimi-zlib-0-119999","i":"fb2","s":51374,"p":"8078","l":"russian","d":"https://url03.ctfile.com/f/64369603-1509339910-ca0aaa?p=8078"},{"n":"16808、_russian_Форт Стеллар_Ливадный Андрей_.fb2__pilimi-zlib-0-119999","i":"fb2","s":62760,"p":"8078","l":"russian","d":"https://url03.ctfile.com/f/64369603-1509339916-03d739?p=8078"},{"n":"16809、_russian_Естественный отбор_Ливадный Андрей_.fb2__pilimi-zlib-0-119999","i":"fb2","s":40868,"p":"8078","l":"russian","d":"https://url03.ctfile.com/f/64369603-1509339922-b19add?p=8078"},{"n":"1680、_russian_Люди мужества_Черешнев Александр Иванович_.fb2__pilimi-zlib-0-119999","i":"fb2","s":82121,"p":"8078","l":"russian","d":"https://url03.ctfile.com/f/64369603-1509339934-88610d?p=8078"},{"n":"16810、_russian_Десант на Счастье_Ливадный Андрей Львович_.fb2__pilimi-zlib-0-119999","i":"fb2","s":99253,"p":"8078","l":"russian","d":"https://url03.ctfile.com/f/64369603-1509339937-292f1e?p=8078"}]