[{"n":"_pilimi-zlib-0-119999_5214、_russian_Мужчины в ее жизни_Брэдфорд Барбара_.fb2","i":"fb2","s":237259,"p":"8078","l":"russian","d":"https://url03.ctfile.com/f/64369603-1509650767-235e13?p=8078"},{"n":"_pilimi-zlib-0-119999_52150、_russian_Лечение болезней почек_Романова Елена_.fb2","i":"fb2","s":78742,"p":"8078","l":"russian","d":"https://url03.ctfile.com/f/64369603-1509650770-590809?p=8078"},{"n":"_pilimi-zlib-0-119999_52152、_russian_Дневник вуарйериста_Бесстыжев А._.fb2","i":"fb2","s":33190,"p":"8078","l":"russian","d":"https://url03.ctfile.com/f/64369603-1509650779-6de270?p=8078"},{"n":"_pilimi-zlib-0-119999_52153、_russian_Сколопендр и планктон_Виан Борис_.fb2","i":"fb2","s":244706,"p":"8078","l":"russian","d":"https://url03.ctfile.com/f/64369603-1509650782-12473e?p=8078"},{"n":"_pilimi-zlib-0-119999_52154、_russian_Лунь_Клочков Сергей_.fb2","i":"fb2","s":261810,"p":"8078","l":"russian","d":"https://url03.ctfile.com/f/64369603-1509650785-53e754?p=8078"},{"n":"_pilimi-zlib-0-119999_52155、_russian_Правила для революционеров. Создавай как бог управляй как король работай как раб_Кавасаки Гай_.fb2","i":"fb2","s":142134,"p":"8078","l":"russian","d":"https://url03.ctfile.com/f/64369603-1509650791-45d58a?p=8078"},{"n":"_pilimi-zlib-0-119999_52156、_russian_Противоположности_Засецкая Татьяна_.fb2","i":"fb2","s":787409,"p":"8078","l":"russian","d":"https://url03.ctfile.com/f/64369603-1509650794-e23073?p=8078"},{"n":"_pilimi-zlib-0-119999_52157、_russian_Вольный Ветер_Засецкая Татьяна_.fb2","i":"fb2","s":860065,"p":"8078","l":"russian","d":"https://url03.ctfile.com/f/64369603-1509650800-05658a?p=8078"},{"n":"_pilimi-zlib-0-119999_52158、_russian_Ставка - Жизнь_Засецкая Татьяна_.fb2","i":"fb2","s":1213593,"p":"8078","l":"russian","d":"https://url03.ctfile.com/f/64369603-1509650803-69f7f5?p=8078"},{"n":"_pilimi-zlib-0-119999_52159、_russian_ДРЕВНИЙ РИМ. СОБЫТИЯ. ЛЮДИ. ИДЕИ._Утченко Сергей Львович_.fb2","i":"fb2","s":273021,"p":"8078","l":"russian","d":"https://url03.ctfile.com/f/64369603-1509650806-58ad84?p=8078"},{"n":"_pilimi-zlib-0-119999_5215、_russian_Золотые яблоки Солнца_Брэдбери Рэй_.fb2","i":"fb2","s":6825,"p":"8078","l":"russian","d":"https://url03.ctfile.com/f/64369603-1509650809-94d6bb?p=8078"},{"n":"_pilimi-zlib-0-119999_52160、_russian_Цицерон и его время_Утченко Сергей Львович_.fb2","i":"fb2","s":339314,"p":"8078","l":"russian","d":"https://url03.ctfile.com/f/64369603-1509650812-256b87?p=8078"},{"n":"_pilimi-zlib-0-119999_52161、_russian_Страж_Пехов Алексей Юрьевич_.fb2","i":"fb2","s":821546,"p":"8078","l":"russian","d":"https://url03.ctfile.com/f/64369603-1509650815-1dfbe3?p=8078"},{"n":"_pilimi-zlib-0-119999_52163、_russian_Начало пути_Распопов Дмитрий Викторович_.fb2","i":"fb2","s":386567,"p":"8078","l":"russian","d":"https://url03.ctfile.com/f/64369603-1509650821-12fecd?p=8078"},{"n":"_pilimi-zlib-0-119999_52164、_russian_Там_Борисова Анна_.fb2","i":"fb2","s":197927,"p":"8078","l":"russian","d":"https://url03.ctfile.com/f/64369603-1509650824-199e1a?p=8078"},{"n":"_pilimi-zlib-0-119999_52165、_russian_Креативщик_Борисова Анна_.fb2","i":"fb2","s":172164,"p":"8078","l":"russian","d":"https://url03.ctfile.com/f/64369603-1509650830-407c8c?p=8078"},{"n":"_pilimi-zlib-0-119999_52166、_russian_Прямо до самого утра или Секрет неприметного тупичка_Верещагин Олег Николаевич_.fb2","i":"fb2","s":383566,"p":"8078","l":"russian","d":"https://url03.ctfile.com/f/64369603-1509650833-5ce788?p=8078"},{"n":"_pilimi-zlib-0-119999_52167、_russian_Он призвал меня_Мюллер Йорг_.fb2","i":"fb2","s":98808,"p":"8078","l":"russian","d":"https://url03.ctfile.com/f/64369603-1509650836-c848e7?p=8078"},{"n":"_pilimi-zlib-0-119999_52168、_russian_Осада Ченстохова_Крашевский Юзеф Игнаций_.fb2","i":"fb2","s":410637,"p":"8078","l":"russian","d":"https://url03.ctfile.com/f/64369603-1509650839-007611?p=8078"},{"n":"_pilimi-zlib-0-119999_52169、_russian_Поумнел_Боборыкин Петр Дмитриевич_.fb2","i":"fb2","s":168002,"p":"8078","l":"russian","d":"https://url03.ctfile.com/f/64369603-1509650842-4afad4?p=8078"}]