[{"n":"_pilimi-zlib-0-119999_71140、_russian_Касательно порядка публичного богослужения_Лютер Мартин_.fb2","i":"fb2","s":6467,"p":"8078","l":"russian","d":"https://url03.ctfile.com/f/64369603-1510089802-3c8a28?p=8078"},{"n":"_pilimi-zlib-0-119999_71141、_russian_К христианскому дворянству немецкой нации_Лютер Мартин_.fb2","i":"fb2","s":102029,"p":"8078","l":"russian","d":"https://url03.ctfile.com/f/64369603-1510089805-aec386?p=8078"},{"n":"_pilimi-zlib-0-119999_71142、_russian_К советникам всех городов_Лютер Мартин_.fb2","i":"fb2","s":33186,"p":"8078","l":"russian","d":"https://url03.ctfile.com/f/64369603-1510089808-d90893?p=8078"},{"n":"_pilimi-zlib-0-119999_71143、_russian_Из переписки Мартина Лютера и Эразма Роттердамского_Лютер Мартин_.fb2","i":"fb2","s":11785,"p":"8078","l":"russian","d":"https://url03.ctfile.com/f/64369603-1510089811-0b5c93?p=8078"},{"n":"_pilimi-zlib-0-119999_71144、_russian_95 тезисов_Лютер Мартин_.fb2","i":"fb2","s":7971,"p":"8078","l":"russian","d":"https://url03.ctfile.com/f/64369603-1510089814-9f9d4b?p=8078"},{"n":"_pilimi-zlib-0-119999_71145、_russian_Кольцевая автомобильная дорога Санкт-Петербурга. Справочник_нет_.fb2","i":"fb2","s":595893,"p":"8078","l":"russian","d":"https://url03.ctfile.com/f/64369603-1510089817-fffe48?p=8078"},{"n":"_pilimi-zlib-0-119999_71146、_russian_Проповедь об отлучении_Лютер Мартин_.fb2","i":"fb2","s":18775,"p":"8078","l":"russian","d":"https://url03.ctfile.com/f/64369603-1510089820-330940?p=8078"},{"n":"_pilimi-zlib-0-119999_71147、_russian_Вардананк_Демирчян Дереник_.fb2","i":"fb2","s":699999,"p":"8078","l":"russian","d":"https://url03.ctfile.com/f/64369603-1510089823-a1333f?p=8078"},{"n":"_pilimi-zlib-0-119999_71148、_russian_Истории из армянской истории_Налбандян Карен Эдуардович_.fb2","i":"fb2","s":28249,"p":"8078","l":"russian","d":"https://url03.ctfile.com/f/64369603-1510089826-e4fbe2?p=8078"},{"n":"_pilimi-zlib-0-119999_71149、_russian_Что такое КВН_Марфин Михаил Чивурин Андрей_.fb2","i":"fb2","s":184591,"p":"8078","l":"russian","d":"https://url03.ctfile.com/f/64369603-1510089829-65f528?p=8078"},{"n":"_pilimi-zlib-0-119999_7114、_russian_Браконьеры_Больных Александр_.fb2","i":"fb2","s":4131,"p":"8078","l":"russian","d":"https://url03.ctfile.com/f/64369603-1510089832-095228?p=8078"},{"n":"_pilimi-zlib-0-119999_71150、_russian_Знаете ли вы что…__.fb2","i":"fb2","s":79802,"p":"8078","l":"russian","d":"https://url03.ctfile.com/f/64369603-1510089835-6e654a?p=8078"},{"n":"_pilimi-zlib-0-119999_71151、_russian_Потери знамен и штандартов Российской Императорской армии в 1799 – 1917 г.г._Шевяков Тимофей Николаевич_.fb2","i":"fb2","s":37458,"p":"8078","l":"russian","d":"https://url03.ctfile.com/f/64369603-1510089841-7202cc?p=8078"},{"n":"_pilimi-zlib-0-119999_71152、_russian_Иерусалимские дневники_Эзер Михаил_.fb2","i":"fb2","s":104409,"p":"8078","l":"russian","d":"https://url03.ctfile.com/f/64369603-1510089844-56d8b8?p=8078"},{"n":"_pilimi-zlib-0-119999_71153、_russian_Как дешифровать новости государственного ТВ_Латынина Юлия_.fb2","i":"fb2","s":8895,"p":"8078","l":"russian","d":"https://url03.ctfile.com/f/64369603-1510089847-bdac3d?p=8078"},{"n":"_pilimi-zlib-0-119999_71154、_russian_Каменный Пояс 1982__.fb2","i":"fb2","s":1192111,"p":"8078","l":"russian","d":"https://url03.ctfile.com/f/64369603-1510089850-94f68f?p=8078"},{"n":"_pilimi-zlib-0-119999_71155、_russian_Каменный Пояс 1982__.fb2","i":"fb2","s":1091695,"p":"8078","l":"russian","d":"https://url03.ctfile.com/f/64369603-1510089853-c5595a?p=8078"},{"n":"_pilimi-zlib-0-119999_71156、_russian_Секс (выдержки из книг)_Раджниш Бхагаван Шри_.fb2","i":"fb2","s":24616,"p":"8078","l":"russian","d":"https://url03.ctfile.com/f/64369603-1510089856-d98f32?p=8078"},{"n":"_pilimi-zlib-0-119999_71157、_russian_Александр Маслов. Земля без Пощады.__.fb2","i":"fb2","s":93180,"p":"8078","l":"russian","d":"https://url03.ctfile.com/f/64369603-1510089859-02c78c?p=8078"},{"n":"_pilimi-zlib-0-119999_71158、_russian_2009 № 1_ _.fb2","i":"fb2","s":879001,"p":"8078","l":"russian","d":"https://url03.ctfile.com/f/64369603-1510089862-89eb78?p=8078"}]