{"013十":"TysQAFUrEAA=","015夜店外文混搭house电音跳舞大碟no1":"opEQAKOREADTlxAA","015年巴西男女说唱hous":"wkIQAA==","015精选极致动听金牌靓音伤感发烧女声高音质极品黑胶":"z5cQAA==","015阿玛尼包房珍藏全英文经典":"D0oQAA==","023头版24bit":"8JcQAA==","05日":"+ZIQAA==","0精":"USQQAFIkEAA=","11三":"j04QAA==","12爵":"AY4QAA==","12环":"/48QAA==","13超":"wI4QAA==","15劲":"CDsQAENOEAB0TxAAjI4QANOPEACEkBAAO5MQAEVOEAAElRAABZUQAA==","15巅":"Do0QAA==","16届":"UisQAFMrEABYKxAA","19首高音质黑胶车载hqcd天":"CpcQAA==","2015潮流时尚打造本色酒吧":"l1AQAA==","2015潮牌时尚打造酒吧中场高档次气氛弹跳电音节奏mashuphousee舞":"u5IQAA==","2015阿玛尼夜店潮流经典高档次强劲弹性hous":"+0EQAA==","2015顶级夜店音乐酒吧昧场伤感中文funkyr":"l48QAA==","2015风靡全球夜店至尊v":"CUoQAA==","2017广州国际音响展览":"0iQQANMkEAA=","2020头版限量编号24k":"+Y8QAA==","20首":"d4cQAHSIEADxlxAAaScQAPw4EADxUBAAmJYQAJGXEABWJBAAdycQAEs7EADSShAA","4輯":"ryMQAA==","5年":"QkAQAN5QEACdihAANosQAG8mEAB0MBAAHzUQAA07EABsPRAAwkIQAFxMEAC6TxAAvyMQADQxEAA=","5火爆情歌慢":"4ZEQAA==","5精选优雅动听柔情流行情歌靓音发烧男女声高音质黑胶车载hqc":"C0oQAA==","6潮":"jY0QAJuQEAA=","8分钟柔情磁":"9jwQAA==","90周":"BzcQAA==","c小":"l0sQAF1MEABDThAAVVEQAB2SEAA7kxAAxpQQAMuWEAA9MRAARToQADVBEAAAihAARJAQAHeSEAA=","deluxe":"tCQQAA==","dj经典中文情歌车载":"MEEQAA==","dj陈川向全世界的朋友拜年了":"04cQAA==","dvorak":"0IYQAIYmEACbJhAAy0sQAA==","enesis":"8YoQAA==","estlif":"FZUQAA==","fi伤感连版试音碟曾":"loYQAA==","housec":"CJYQAApKEACZiRAAzI4QAAOQEABakBAA","house毒嗨":"IZEQAA==","ifi聆听30首经典发烧情":"Nz4QACNAEAA=","j偷":"SjUQAGQ1EAA=","op音乐与徒弟dj小莞一起享尽":"S5YQAA==","phop舞曲串烧":"CVMQAHCUEAA=","rofunky强劲电音慢摇毒":"0jsQAA==","spa入眠2cd":"aZYQAC2XEAA=","stlife":"FZUQAA==","s瑜":"oJYQAA==","uecolo":"ypYQAA==","vening":"6ScQAA==","一听天":"94oQAA==","一首诗":"n5UQAA==","七彩的":"8Y4QAA==","万语disc05":"ADUQAA==","万语disc14":"CTUQAA==","上华群":"z5EQAA==","上天入地hous":"I1MQAA==","上最好":"KIwQAA==","不厌十六首":"b0AQAA==","不可多":"pYcQAA==","不想伊":"cSgQAI0oEAA=","世纪传唱系列8cd":"3i4QAOAuEADiLhAA5C4QAOUuEADmLhAA5y4QAN8uEADhLhAA4y4QAA==","东方旅":"oJIQAGGTEAA=","个季节":"TzQQAFA0EABRNBAA","个理由":"PokQAA==","中国老":"5Y0QAKiOEABrjxAAJY0QAA==","中文多":"wpQQAA==","中文极品慢":"uj0QAA==","中文超":"nkYQAA==","中英文顶级dj慢嗨大":"WYcQAA==","丽性感":"YTUQAEc1EAA=","乐网慢":"N40QAA==","二十年":"YCoQAGEqEABjKhAA7DcQAAY5EACAiRAA4pUQAKaWEABiKhAAVTsQACKVEABplxAA","仓央嘉":"DEQQAFxGEADtlhAA","他天皇":"SykQAEwpEABOKRAATykQAFEpEABSKRAARSkQAA==","们的歌":"ZDoQAJVOEADATxAALZAQAPGQEAAakRAA2pEQAA==","伤寒杂":"akoKAA46EAA=","低音提":"jyYQAA==","低音极":"M1AQAEaWEAA=","兄弟辛":"jpcQAA==","兄难弟":"2JYQAA==","克斯风5":"b5AQANaTEAA=","全神曲":"kI4QAA==","全英文mashup苏荷soh":"CZUQAA==","全行驶":"AzQQAPOIEABejBAA","典14":"gDkQAA==","典e":"0jsQAA==","典伤感":"IpEQAIWVEABgRxAAHE0QAA==","刘文正1":"KSkQACopEAAsKRAALSkQADApEAArKRAALikQAC8pEAAnKRAAKCkQAA==","创概念":"WkYQAA==","初次尝":"uSMQAA8xEAAZNRAA","别的海":"iygQAA==","加拿大":"CpMQAA6HEAAwiBAA","动听靓音发烧磁性女声高音质极":"DkUQAA==","劲爆狂嗨不":"Xj0QAA==","北京到":"IEcQAA==","千年之":"8JcQAA==","厅热门动感":"F5AQAA==","原音母":"WEMQAOmGEABTNhAAB0EQAINCEAA=","去秋来":"YkMQAA==","古琴新":"u0YQAA==","后我该怎么":"KH4QAA==","向全世界的":"04cQAA==","听f":"TI4QAA==","听勿扰":"skYQAA==","听必哭":"h0MQAA==","听精采":"KpMQAA==","听钟秦":"mSoQAJoqEAA=","命运的":"k5AQAA==","和我去成都":"+IkQAA==","响低音":"nEYQACZ0EACVjxAA","响醉美草原动听专辑高音质黑胶":"YIoQAA==","唐人舞":"gTAQAA==","唱着情歌流":"+zcQAA==","嗨c":"940QAL6PEAA=","四季歌":"GCkQABwpEAC8iRAA","国语情":"QDcQAA==","土高坡":"U4sQAA==","在希望":"dy4QAA==","域d":"WYcQALyHEADMjhAAG5IQAP2SEACBORAAlTwQANNFEADURRAAV1EQAJ+READSOxAAljwQAApKEACWUBAAmYkQAFqQEAAAlBAACJYQANFKEAAzUBAA3YoQAE6NEABJlhAAgz4QACN+EAA=","域外草原的":"vI0QAA==","域情郎d":"IJEQAA==","堪称最":"NDQQAEeQEAA=","声17首高音质极品黑胶车":"Q5QQAA==","声26首高音质极品黑胶车":"X4oQAA==","夜尖叫":"RTQQACI4EAArOBAA1HMQAA==","夜店11月全新中式电音超爽全英文说唱house包房专用":"HIgQAA==","夜店狂潮潮流中文dj":"F5UQAA==","夜店电子mayc":"TY4QAA==","夜店超爽电嗨2015至尊vip中场商业电音hou":"zI4QAA==","天碟③":"Xj0QAA==","奇藏巴":"sDwQAA==","奔向彩":"hokQAEBREABChxAA","女声20首极品黑胶车载hqcd天碟":"kZcQAA==","女声黑胶车载cd":"TkQQAKpOEAA=","委婉优":"7IoQAA==","姚璎格":"nyMQAKcjEACsIxAAn0IQAFRPEAB2UBAAmFEQAHdLEAChIxAApCMQAKYjEADDORAA6FAQAJmHEAAtiRAAoyMQAKUjEACoIxAAP0cQAAd+EAC7iBAAjokQAN6JEADvRBAA","娃新曲":"YC8QAGEvEAA=","娘20":"z5YQAA==","子e":"BFMQACeTEAA=","子乐队":"PYgQAA==","完美篇":"XUQQAA==","宝莲灯":"/jUQAA==","室酒吧内部":"1o8QAA==","尊h":"4JEQAA==","小琥专":"bz0QAA==","小黎重现经典天龙大道劲爆串烧":"RJAQAA==","尚打造酒吧夜店主流包房说唱气氛英文节奏hou":"fZMQAA==","尚震撼":"g0MQAA==","工行谁":"y40QAA==","巴克与":"5zsQAA==","年5":"wyMQAMQjEACMJBAA/TQQABs1EAC7IxAA","年义演晚会实况录音纪":"rycQAA==","庆20":"MH4QAA==","店vip王者本色2015至尊tur":"1I8QAA==","式限定":"MCMQAA==","待客全":"JlMQAA==","得用狠":"i5YQAA==","志安魂":"dyYQAIwmEADMUBAA","念发烧":"p5QQAA==","性女声二十一首高音质极品黑胶":"hUMQAA==","情场就":"QScQAA==","情对话":"0ZcQANuQEABllBAA","情巨作":"sDwQAA==","情粤语":"YocQAA==","惠专辑":"kpQQAA==","感主流酒吧中场英文电音节奏house":"d40QAA==","愿做个":"eo0QAA==","成名作2":"dy0QAA==","我亲爱":"1E8QAA==","我心中":"1DkQABqWEAA=","打造2015电音新势力震撼登场全外文edm极":"EpgQAA==","打造夜店主流动感越鼓英文节奏electrohou":"T48QAA==","技音质":"iY0QAA==","指弹一":"aCUQAHAlEAA=","推荐串":"1o8QAA==","提琴我知道":"QkgQAA==","提琴第":"P5EQAP+REAA=","摇摆现场顶级全英文housecl":"mYkQAA==","播20":"hJAQAA==","文志韩":"EisQAOKJEAA=","文电能量重":"+UEQAA==","斯坦福":"tpUQAA==","施坦威":"H0oQAPOOEAC4jxAA","日凉爽电能量上天入地house狂嗨慢摇串":"I1MQAA==","时尚慢":"FH4QAA==","星19":"WCkQAFkpEABVKRAAVikQAFcpEAA=","星风华璀灿":"GYoQAJc/EACJRhAA1IcQAPaIEADoQRAAOUQQANZIEADBShAAsoYQAA==","是风儿":"b5cQAA==","晓东remix":"zY4QAA==","最动听的古":"uIYQANqHEAA=","望北京":"AJMQAA==","朱晓琳":"PDAQAMZFEABMTBAA","极品慢摇串":"H0gQAA==","极致发烧靓":"NYsQAA==","梦的翅膀受":"XZAQAA==","歌35":"HZEQAA==","歌h":"8kEQAHhCEADJRBAA5EUQAJtGEAAdjBAAoT8QAA==","歌曲无":"Rk0QAKxPEAA=","泪下的":"EY8QAA==","洁l":"3CwQAIk6EAA=","洋20":"CYcQACuIEABNiRAAb4oQAAhREAA=","洋b":"oioQAA==","活2":"YSkQAGYpEAA=","派名剧":"NDAQAA==","流时尚打造夜店主流动感电音英文节奏elec":"KX4QAA==","流经典":"+0EQAA2OEAA=","流行情歌靓":"C0oQAA==","海首版":"8y8QAA==","深玫色酒吧包房英文电音funkyh":"E1MQAPmWEAA=","清又纯":"lSwQAA==","港压非":"hY8QAA==","游戏一":"+SsQAECQEAA=","湾福茂":"2kEQAABNEABILBAAVCwQAGgsEADJLBAAiT8QAA==","滚金曲":"dFEQAA==","演唱者都是当代歌坛明星和梨园":"RIsQACk4EAA=","演饭拍":"1y8QAA==","火火中":"UpcQAA==","烧v":"GVMQAH6YEAA=","烧音色":"AosQAA==","热门歌曲串唱ape":"UTAQAA==","然情诗2":"b5EQADCSEAA=","爆一场不可收拾的dj狂潮":"+IgQAJuOEAA=","爱一次":"xkIQAA==","爱乐团":"7o4QAA==","爱你那":"EEgQAA==","爱到痴":"cUMQAM6UEADOOBAA","爱在靠":"RowQAA==","爱的空":"HU8QAD9QEABhURAA","片东芝1":"UDEQABJNEAA=","版辽宁":"yE4KAEM/EAA=","特色超":"dogQAA==","玛尼夜店震撼经典档次house毒":"IZEQAA==","现11":"rDQQAA==","现在开":"JTEQAA==","珍藏绝版私":"0jsQAA==","生活故":"HpYQAA==","用d":"DSkQABApEAARKRAAEikQABMpEAAUKRAACykQAA4pEAAPKRAAB40QAAopEAAMKRAA","用嗨碟":"HIgQANCXEAA=","男极声":"PSgQAPIoEAA=","疼入心":"qjUQAA==","病百问":"LFMKAHBIEAA=","百分百":"wSgQADKQEAD2kBAA1JIQAMAoEAA=","的低音":"jyYQAA==","的你在":"9DwQAPmOEAA=","的听觉典范":"VocQAA==","的呼声":"5jcQAA==","的姑娘草原":"UI8QAA==","的颤音":"gyYQAA==","真爱是":"+TAQAIs6EAA=","硬货版":"hZQQAA==","福经典":"oSUQAAFIEAA=","秋之律":"80AQAA==","粤语情":"uocQAA==","精选全球最":"xZUQAA==","精选包房必备气氛经典商业英文club慢摇串":"iI0QAA==","精选碟包内":"qj8QAA==","系列复":"QE4QAN+GEACdjxAA6JEQANeWEAA=","红hifi靓声倾":"epMQALiSEAA=","经典一":"YCgQAJkoEABjmBAA","经典发烧情":"Nz4QACNAEAA=","经典流":"4pUQAKaWEABplxAAIpUQAA==","络流行":"hTkQABGYEAA=","网络才":"njkQAGFPEAA=","美歌声极品女人3d环绕商":"T40QAA==","肆意疯长的":"UUQQAA==","胸椎病怎么":"JEoKAAw6EAA=","腔贺岁":"GCsQABkrEAAeKxAALSsQAN2GEAA=","致优美动听18首发烧磁性女声":"XJAQAA==","致靓音动听情感发烧磁性女声21首高音质极品黑胶车载hqcd天":"DJcQAA==","航m":"IzYQAFuKEAA=","色中文":"jI4QAA==","色醉人年度经典动听情感发烧女":"qk4QAA==","艳色中文2015劲爆dj":"jI4QAA==","芳20":"GVAQADxREAAuRBAAfkYQAMtIEAC2ShAABE0QAO1OEAA=","若拾香":"/IoQAA==","英雄泪":"9SsQAA==","苹果花":"UCcQAA==","菲比国际俱乐部摇摆现场顶级全英文houseclu":"mYkQAA==","藏全英文经典重弹ele":"D0oQAA==","行歌林招牌":"qC8QAJ4vEACgLxAA","视原创配乐":"Pk0QAA==","诉我亲":"1E8QAA==","诱惑邂逅相":"BTkQAA==","调歌后2":"0CwQAA==","超叼重鼓中场houseclub顶级电音劲爆":"CkoQAA==","超爽电嗨2015至尊vip中场商业电音hous":"zI4QAA==","跟狗一样2015网络中文":"xpUQAA==","轰炸全球顶尖欧美潮范高档":"gD4QAA==","载极速":"z44QAA==","选2c":"m48QACAxEAAhMRAAljIQAFA7EACviBAAlTIQAJ89EAB5RhAAjYcQAA==","选疗伤情歌":"EZgQAA==","造苏荷8":"WEwQALyKEAA=","造飞机":"SkAQAA==","郑智化2":"lioQAIwqEACNKhAAlSoQAA==","部神经":"1EUQAA==","郭英男":"QD4QAA==","都市民":"dT4QAA==","酒吧首选嗨":"FZAQAA==","酒場演":"nTAQAA==","醉美伤":"9kEQAA==","重弹气氛电子dub":"0UUQAA==","金88极品":"pYkQAH+LEADuMxAAcosQANQiEADnMxAAEYwQAMuMEADglxAA3iIQAAwxEAAfjBAAJ4wQADGMEAA+jBAASowQAOgiEADiMxAA9TMQAA==","银版浅镀透明光":"kzoQAA==","银色的月光":"GSkQAB0pEAA=","限量版24":"P0cQAA==","雅专辑":"HzsQAA==","雨半山":"SEcQABB+EAA=","零度夜店主流英文电音house节":"jY0QAA==","音响专":"s4kQAAeWEACOlxAAEZgQABMpEAD1hhAACykQAA4pEAAUKRAAc5EQAJGSEAAMKRAADSkQABApEAAblxAAmZUQAJqJEAAHjRAAKUAQAAopEAAPKRAADDsQAII+EAAWTxAAEikQAKaHEAAbiBAAkIgQAMiIEAA1khAA/5IQAICTEACGlBAA1pQQABEpEAD4QRAAekIQAElEEAA=","音响低":"JnQQAJWPEACcRhAA","音监听":"p08QAA==","音质蓝光车载cd金碟":"hZUQAA==","音领域":"NEEQANJPEAC4hxAA/4kQAMiVEACTlxAA+IwQAI2NEADPOxAAC1MQAJ+JEAABihAAko8QAMyOEACHlRAA6kgQANJKEADHlRAAKlMQACFIEACYPBAA2ogQALySEACBORAAVlEQAE6NEAAAkxAAgz4QADVQEACWUBAABlMQANyIEADSjxAAmYkQAJ+REAAiNhAAlTwQAFtHEADfihAAWpAQAFyQEAD9khAAljwQAIiVEADTOxAAB1MQAP+XEABhRxAAuj0QANFKEABVURAAjI0QANI7EACdiRAADY8QAFCXEABVhxAAEI8QAN2KEAAIOxAAjY4QAAtKEAD9iRAAHJEQAEqVEABZhxAAWEwQABeIEAAjfhAAmjwQAApKEADGlRAAjJYQAFKXEABeRxAAOzEQAEg6EACFQxAAG5IQAB6SEACJlBAA85QQAE+XEACEPhAAW1EQAF+KEADUjxAAfZMQAEmWEADURRAA6EgQAAuWEAAnUxAAmpAQAImWEAD2QRAAIkgQAKpOEACXUBAAV1EQAACUEADMlhAAz5cQADYxEADUShAAM1AQALyHEABXkBAAq5MQAM+WEAAXUxAA00UQAHiIEAB6khAA65MQAIWVEACZRhAAxZUQAAiWEACZPBAArD8QACCREAC7khAATJcQAA==","首版签":"g4gQAA==","高烧男":"GjMQABszEAA=","高质量":"+ygQAPwoEAD4KBAA+SgQAPooEAA=","黄金十年老":"IDsQAHA9EAA=","龙梅子":"R0QQAAVNEABuhxAAL0QQAMxIEAC3ShAA+zMQABpQEABtURAA3kEQAB5FEAAjSBAA7k4QAEtQEABTjBAA"}