{"000年史":"xNkBAA==","060人生":"Zq8BAA==","0岁恋爱也不晚":"twACAA==","0年现代化":"3oUBAA==","0应用维护":"IGUBAA==","0搭建大规":"tmQBAA==","10亲爱的生":"W6QBAA==","1世纪关涉":"QQYAACsAAAA=","3伊甸之东":"wKQBAA==","3讲给大家的中国历史1中国":"Wa8BAA==","400年至":"wbQBAA==","49年中":"DqMBAA==","8位基金经理的":"ucgBAA==","cgis的pyt":"g2UBAA==","c自然探索":"CXcBAOSJAQARSwAA","dn环境部署与ope":"YIQBAA==","eg从入":"J2QBAA==","elenium自":"EGQBAA==","e词汇精选":"ZHMBAMJrAQA=","hon和nump":"FGMBAA==","ndows黑客编程技":"G2UBAA==","ndroid应用程":"qoQBAA==","opendaylight":"YIQBAA==","os开发":"D2MBAImEAQCKhAEA","python全案例":"vIQBAA==","p原型制作":"nIQBAA==","r和spring":"pGIBAA==","ty3":"zmMBAM9jAQA=","uino与labview开":"V2QBAA==","x指令从入":"LGUBAA==","万象的思想精":"BYcBAA==","下了解和影响":"pr0BAKe9AQA=","专业人士":"y4gBAA==","业核心课":"7wYAAFgyAQB+dgEA+4gBAA==","业级容器":"22UBAA==","个体心理学最":"A84BAA==","个益智推理谜":"P/IBAA==","个词是怎么来":"wLABAA==","中国文化知识":"Af8BAAL/AQA=","中国青年":"Jp0BACidAQA=","主的优秀作品":"EocBAA==","丽洁202":"HaMBAA==","之遗民与贰臣":"+rUBAA==","于决策与判断":"a+sBAA==","人民文学出版":"gZwBAB+dAQCdnAEA1ZwBAD2dAQCFnQEAFocBAAiJAQCfnAEAqZwBAOGcAQDjnAEAEZ0BABOdAQBJnAEAS5wBAIWcAQClnAEA05wBAB2dAQA5nQEAh50BAD9QAQDShwEA","人流沙河":"D4cBAA==","人陪你颠":"xfUBAA==","从原子到经济":"XPIBAA==","从电影租赁店到在线视频新巨":"d9MBAA==","以及写作习惯":"5YUBAA==","以经济视角剖":"6oYBAA==","仪藏宝录2":"TuYBAA==","们只是讲道理":"iucBAA==","们应对现":"RwAAAHAGAAA=","们易被偏见左":"/MgBAA==","任教你吃出健":"TfsBAA==","企业财务管理":"388BAA==","会主义核心价值观经典名句实用手":"eVIBAA==","伦比亚中":"z7UBAA==","何形成的以及对人类现实行为":"R3IBAA==","作为自由前提":"/qIBAA==","作文素材20":"4fUBAOL1AQDd9QEA3vUBAN/1AQDg9QEA","你该找个":"hL8BAA==","信息系统":"PWUBAJ2EAQBEwwAAR8MAAEjDAABJwwAAVsMAAFjDAAA=","克里科幻小说":"7bQBAA==","全面的屠格涅":"z4cBAA==","内核设计思想":"rmQBAA==","军舰珍妮特号的极":"J7QBAA==","创国产动画反":"AYgBAA==","别相信任":"cfYBAKX8AQCm/AEA","制时代人":"/bUBAA==","务史上13大":"ALEBAA==","务报表阅读与":"BLEBAAOxAQA=","动态网站开发从入":"fmQBAA==","动手做交互系":"NWMBAA==","劳利的海洋征":"KIcBAA==","化时代的企业":"YPIBAA==","历史的另一种可能":"I/YBAA==","原书第13版":"x34BAA==","只是对人":"MPQBAA==","史上最经典的2":"V/sBAA==","合的芒果实践报告":"uu4BAA==","名品牌只做不说的营销":"MvsBAA==","启商业与未来":"Lv4BAA==","和你身边":"MHMBAA==","和平中的一生":"8dgBAAbeAQA=","唐江2016":"fLQBAA==","唐诗宋词诗经":"j5UBAA==","嘉莹先生作品10":"0IUBAA==","器学习系":"A2MBAA==","四次咖啡革命":"YvQBAA==","国妈妈育儿经":"SdUBAA==","国家命运":"BuMBAP/xAQA=","国就是这":"jeoBAI7qAQCP6gEA","国心理协会反焦虑":"JpgBAA==","国精神五":"z9kBAA==","在精神病院抗":"fecBAA==","夏则大与渐慕华风":"XrQBAA==","大做强的关键":"HM4BAA==","大夫政治":"rLQBAA==","大数据实战权威指":"kmMBAA==","头的10大关":"7rABAA==","女性最讨巧的升职":"vP8BAA==","她是幸存":"bqMBAA==","好人生运":"mL8BAA==","如果你爱上了":"lfkBAA==","妙趣横生的创意思":"uP8BAA==","始人精神":"xfcBAA==","威士忌原来是":"we4BAA==","婴儿护理百科":"6MIAAA==","学院教育教学":"PGUBAA==","宇澄2013":"Y7UBAA==","安石及其新政":"PaMBAA==","实现真正的增":"1s8BAA==","家古籍整理出":"3IcBAA==","密与解决方案":"VWMBAA==","对不可预知的":"yU8BAA==","导力驱动型公":"yrQBAA==","寿彝史学":"G4YBAA==","小说图书":"U7QBAA==","就是这样":"IOYBAA==","尼安德特":"vwUAAAMGAABLrwEA","嵌入式linux与物":"DGUBAA==","巴黎陷落":"y2sCAA==","市社会科学理论著作出版基金重点资助":"24kBAA==","布斯的管理课":"gP4BAA==","师德鲁克回忆":"IM4BAB/UAQA=","年会计从":"wQACAA==","年决定一生的":"b/4BAA==","并非不快":"DpgBAA==","序设计丛":"3ogBAA==","库应用与开发":"c2QBAA==","应对美国":"tfABAA==","庭问题背后的心理":"7QQAALwGAAA=","建筑电工":"hPcBAA==","开的殿堂级著":"GYkBAA==","当之无愧的畅销天":"CYYBAA==","彦桦201":"U7UBAA==","心系统命":"8WQBAA==","忆小说精":"2oUBAA==","忙碌者的天体物理":"VrQBAA==","快速开发与实":"9mIBABtkAQA=","念的根治":"ty8CAA==","态下的变革与决策":"Y6cBAA==","思贤2021":"77UBAA==","情场不输人职":"6/UBAA==","成功品牌的20条法则":"XfQBAA==","我们是如何被四项关键生存特性摧毁的":"p/QBAA==","我的人生哲学":"EfQBAA==","我的第一本销售入":"BfQBAA==","战争主题套装":"G4cBAA==","战争和伯罗奔":"xIcBAA==","所咨询顾问共":"vokBAA==","执着如一地追":"sokBALaJAQCuiQEAs4kBALSJAQC1iQEAt4kBALiJAQCviQEAsIkBALGJAQA=","持续高速增长":"LL0BAA==","指数基金投资至简":"TOMBAA==","挖掘与机器学":"tWUBAA==","故事讲透生活":"034BAA==","故事隐射社会":"HYcBAA==","教你10秒钟":"mgACAJsAAgA=","教育著名的教育家":"84gBAA==","文与日本之美":"SfABAA==","文化必读经典":"l1IBAMJzAQD/cwEAAnQBAA==","斯与新世界无":"qu4BAA==","斯纪念套":"nOYBABvrAQA=","新赛道引领竞":"EYYBAA==","族工商业巨擘":"BLcBAA==","无线网络":"E2UBADllAQA=","日本推理小说":"GocBACSHAQAuhwEA","日本最受欢迎的职":"T90BAA==","时漫画帝":"sYABAMOBAQA=","星花2015":"KPABACnwAQAq8AEA","最全的冷笑话集锦":"CmwBAA==","术解析与实战":"JGMBAA==","机网络工":"qsYBAA==","杂志2015":"0vUBANP1AQDU9QEA0fUBAA==","杂志和一个时":"tCQDAA==","李嘉诚给年轻人的财富管理课":"/O0BAA==","来刊行的学术成果":"2ocBAA==","来自十二个星球的":"8+0BAA==","栈工程师一本":"y2QBAA==","核心设计":"8mMBAA==","格律读本":"3HMBAA==","械设计从":"S2UBAA==","梵高书信":"334BAA==","民国政治":"oX4BAA==","河童旅行素描":"raQBAA==","泡沫之夏3":"duYBAA==","津式高效沟通":"0YkBAA==","活下去的理由":"xC8CAA==","活到105":"ca8BAJ1xAQA=","活的重大问题":"KwAAAEEGAAA=","海霞201":"MbQBAA==","灯塔守望者的女儿":"AtUBAA==","爱你就像爱生":"oqQBACi1AQA=","片收藏世界上目前":"9AYAAF0yAQAfiQEA","物质和它们背后的":"8aIBAA==","特致股东的信":"wHIBAN5yAQA=","狄奥多罗斯与":"xIcBAA==","狗钱钱的人生":"0vgBAA==","王阳明心学智":"/uEBAA==","环境部署与opend":"YIQBAA==","现代文化之根":"rIcBAA==","现传统文化之":"rIcBAA==","瑞雪2020":"eqIBAA==","生服务网格istio":"fWMBAA==","生的十次深度":"/wQAAA==","用的高绩效管":"Xq8BAA==","用脑神经科学讲清心理问题的产生原因":"/wQAAA==","画片开创国产":"AYgBAA==","界剧变的中国选择":"vsgBAA==","界泰斗杨宪益":"1IgBAA==","疯狂的世界的真相":"K7cBAA==","白寿彝史学思想精髓的精华读":"G4YBAA==","的中东大变局":"d6IBAA==","的人是如何思考的":"YZYBAA==","的存在主义思":"R7YBAA==","的情绪与食欲":"V70BAA==","的日常心理学":"RXMBAA==","的神秘而不可捉摸":"WjIBABCJAQDxBgAA","的项目化思维":"nsgBAA==","盲必读趣":"DocBAA==","知等中国各领":"zYcBAA==","破解六十四个":"A/8BAA==","破解社会":"MJYBAA==","社区优质":"4lIBAOtSAQAcUwEA","社日语工":"RvABAA==","神秘而不可捉摸的":"WjIBABCJAQDxBgAA","私人部门共生":"uPcBAA==","程序运营招式":"zGQBAA==","符号使用手册":"k1IBAA==","算机软硬":"oWMBAA==","类学家一":"zGsCAA==","精益创业实战":"d9gBAA==","系列作品01":"yWsCAA==","索你的超能力":"4y8CAA==","纳德特朗":"heYBAALrAQA=","线系列丛":"CYcBAA==","组编校订2":"H4cBAA==","经典理论和当":"QpgBAA==","统常用技术及":"EWUBAA==","统文化大百科":"7YYBAA==","绣像封神演义":"sWEBAA==","维诺精选":"IocBAA==","编柴油车故障检修精选300例":"8vEBAA==","罗马帝国":"rb8BAK6/AQCZ3gEAuGsCAMSHAQA=","美军航母上的8":"cs4BAHHUAQA=","美国中央":"/HcBAA==","群体情绪是怎":"g/ABAA==","老师的达人造":"RuYBAA==","考察人类文明":"BIcBAA==","能网页设":"z2QBAA==","舌尖上的中国":"880BAPTNAQD1zQEA780BAPDNAQDxzQEA8s0BAA==","艺术眼系":"GLcBAA==","艾伦201":"FaMBAA==","英海200":"mLUBAA==","营经济发展经":"OrQBAA==","藏的传世经典":"mokBAA==","蜂养大的女孩":"0M8BAA==","融大数据挖掘与分":"imMBAA==","袁腾飞讲二战":"9vMBAPfzAQA=","西方一流思想":"0YcBAA==","西的缩影":"u7UBAA==","诗人的十封信":"PqQBAA==","诗里看诗人风":"B4kBAA==","诞生于秩序与混沌边缘的科学":"jbQBAA==","详解与典型案":"1GMBAA==","语学习丛":"DwACAA==","语晨读美":"0FMBAA==","语言数据可视":"ZoQBAA==","请照顾好":"2rQBAA==","诺登与棱":"qNgBAA==","读中国古":"7YYBAA==","读完它们像服":"k4kBAA==","豆瓣热门民族史图书top":"YLQBAF20AQBetAEAX7QBAA==","资却止步不前":"vvcBAA==","资本主义全球":"wrQBANi0AQA=","软件调试":"4WMBAA==","过你想过的生":"qYMBAA==","还原论者的浪":"yvUBAA==","述新东方":"cucBAA==","适2018年":"IKMBAA==","部人类经":"8OEBAA==","部没有阅读门":"p4kBAA==","里曾经是汉朝":"rYcBAA==","销榜to":"8YcBAA==","长方法论":"N2MBAA==","门化学科普图书top9":"MrQBAA==","青年诗人":"PqQBAA==","频仿真设":"TmQBAA==","首版30周年":"KqQBADekAQA8pAEAPqQBAECkAQAmpAEALKQBADCkAQAzpAEA","高二年级":"v80BAA==","高复购的用户":"O68BAA==","高性能应用开":"fWQBAA==","鲁塞尔到北京":"+U8BAA==","鲁迅论人":"rFMBAA=="}