{"018年度推理":"jQsAAA==","019年最值得":"sAsAAA==","02c6e23693aedc12b5ce4fe5be2bf860":"V4YAAA==","5229977":"LEEAAA==","5287928":"lT4AAA==","5287955":"fj4AAA==","5287964":"Zo8AAA==","5287991":"l48AAA==","5294597":"j48AAA==","5346959":"1JIAAA==","5357876":"/kAAAA==","5443997":"kzkAAA==","5448956":"KDoAAA==","5457848":"gtcAAA==","5476937":"zTwAAA==","5487881":"CogAAA==","5487890":"EIgAAA==","5487908":"RogAAA==","5487917":"BzkAAA==","5526995":"KocAAA==","9年最值得期待":"sAsAAA==","bbc自然":"aioBAA==","一个人的无常":"H/4AAA==","万万没想到用理工":"ij4AAA==","中国政治思想":"5DIAAA==","为什么需要生物学":"hj4AAA==","亞如何處理內亞帝":"3JIAAA==","代東亞如何處理內":"3JIAAA==","们都必须一次":"pAsAAA==","公司如何創造二百":"wZIAAA==","国计算机技术与软件专业技术资格":"PUYAAEhGAABLRgAAukEAAL1BAAC/QQAA5UUAAD9GAABARgAA8doAAMhBAAA2RgAAPkYAAM7aAAC2QQAAvEEAAOlFAAA6RgAA9doAAL5BAADGQQAAykEAAMlFAAA7RgAAPEYAAEZGAAA3RgAAuEEAAMtBAAC7QQAAwEEAAMtFAABKRgAAzNoAAA==","地缘政治三部":"FgQBAF1FAAA=","奖两届得主爱":"yjYAAA==","始学微信公众":"1EYAAA==","学书院系列编":"7gYAAA==","安地斯社會的轉變":"2D8AAA==","已被证实的使":"tz4AAA==","帝國的認同危機與社會":"1JIAAA==","度改变与社会":"kT4AAA==","当代经济学译":"uT4AAA==","心理学研究者和爱好者":"PEIAALtGAAA=","掘人类社会背":"Q+wAAJkCAQA=","改变未来社会和商":"F4cAAA==","海明威齐名的美国":"V0UAABAEAQA=","海豹突击队体":"pkYAAA==","生活和事业瓶颈的":"wIYAAA==","用药心悟从验案中":"mEYAAA==","神派临证用药":"mEYAAA==","统与最高法院的较":"vj8AAA==","胡适的一生智慧和精神":"tY8AAA==","融超级蓝海中":"IoYAAA==","防青少年犯罪":"LAcAAA==","非洲到海洋擴":"Y0AAAA==","騎馬遊牧民眼中的":"O0AAAA=="}