[{"n":"16671、_russian_Легат_Посняков Андрей_.fb2__pilimi-zlib-0-119999","i":"fb2","s":302115,"p":"8078","l":"russian","d":"https://url03.ctfile.com/f/64369603-1509338869-97c9b0?p=8078"},{"n":"16672、_russian_Легат_Посняков Андрей_.fb2__pilimi-zlib-0-119999","i":"fb2","s":249982,"p":"8078","l":"russian","d":"https://url03.ctfile.com/f/64369603-1509338872-ea38b9?p=8078"},{"n":"16673、_russian_Кольцо зла_Посняков Андрей_.fb2__pilimi-zlib-0-119999","i":"fb2","s":330481,"p":"8078","l":"russian","d":"https://url03.ctfile.com/f/64369603-1509338881-aacd56?p=8078"},{"n":"16674、_russian_Кольцо зла_Посняков Андрей_.fb2__pilimi-zlib-0-119999","i":"fb2","s":276252,"p":"8078","l":"russian","d":"https://url03.ctfile.com/f/64369603-1509338887-71d030?p=8078"},{"n":"16675、_russian_Кольцо зла_Посняков Андрей_.fb2__pilimi-zlib-0-119999","i":"fb2","s":316641,"p":"8078","l":"russian","d":"https://url03.ctfile.com/f/64369603-1509338893-640833?p=8078"},{"n":"16676、_russian_Грамота самозванца_Посняков Андрей_.fb2__pilimi-zlib-0-119999","i":"fb2","s":294565,"p":"8078","l":"russian","d":"https://url03.ctfile.com/f/64369603-1509338899-241d59?p=8078"},{"n":"16677、_russian_Новогодняя сказка_Попов Андрей_.fb2__pilimi-zlib-0-119999","i":"fb2","s":47443,"p":"8078","l":"russian","d":"https://url03.ctfile.com/f/64369603-1509338905-79fdbf?p=8078"},{"n":"16678、_russian_Русский маг_Погудин Андрей_.fb2__pilimi-zlib-0-119999","i":"fb2","s":437298,"p":"8078","l":"russian","d":"https://url03.ctfile.com/f/64369603-1509338908-fea2a2?p=8078"},{"n":"16679、_russian_Игрожур (главы 1-7 неокончен)_Подшибякин Андрей_.fb2__pilimi-zlib-0-119999","i":"fb2","s":249755,"p":"8078","l":"russian","d":"https://url03.ctfile.com/f/64369603-1509338911-ad53eb?p=8078"},{"n":"1667、_russian_Череп Гоголя под Ла-Маншем_Черкашин Николай_.fb2__pilimi-zlib-0-119999","i":"fb2","s":10112,"p":"8078","l":"russian","d":"https://url03.ctfile.com/f/64369603-1509338914-19191e?p=8078"},{"n":"16680、_russian_Игрожур (главы 1-7)_Подшибякин Андрей_.fb2__pilimi-zlib-0-119999","i":"fb2","s":249711,"p":"8078","l":"russian","d":"https://url03.ctfile.com/f/64369603-1509338929-48878d?p=8078"},{"n":"16681、_russian_Цикл оборотня_Кинг Стивен_.fb2__pilimi-zlib-0-119999","i":"fb2","s":57985,"p":"8078","l":"russian","d":"https://url03.ctfile.com/f/64369603-1509338932-2638f0?p=8078"},{"n":"16682、_russian_Царь муравьев_Плеханов Андрей_.fb2__pilimi-zlib-0-119999","i":"fb2","s":500231,"p":"8078","l":"russian","d":"https://url03.ctfile.com/f/64369603-1509338938-36628d?p=8078"},{"n":"16683、_russian_Слепое Пятно_Плеханов Андрей_.fb2__pilimi-zlib-0-119999","i":"fb2","s":416294,"p":"8078","l":"russian","d":"https://url03.ctfile.com/f/64369603-1509338941-a3388b?p=8078"},{"n":"16684、_russian_Перезагрузка_Плеханов Андрей_.fb2__pilimi-zlib-0-119999","i":"fb2","s":423261,"p":"8078","l":"russian","d":"https://url03.ctfile.com/f/64369603-1509338947-3b5866?p=8078"},{"n":"16685、_russian_ПЕРЕЗАГРУЗКА_ПЛЕХАНОВ Андрей_.fb2__pilimi-zlib-0-119999","i":"fb2","s":370143,"p":"8078","l":"russian","d":"https://url03.ctfile.com/f/64369603-1509338950-0968bd?p=8078"},{"n":"16686、_russian_Левый глаз (сборник)_Плеханов Андрей_.fb2__pilimi-zlib-0-119999","i":"fb2","s":384418,"p":"8078","l":"russian","d":"https://url03.ctfile.com/f/64369603-1509338959-6cd22a?p=8078"},{"n":"16687、_russian_Встречи на футбольной орбите_Старостин Андрей Петрович_.fb2__pilimi-zlib-0-119999","i":"fb2","s":244078,"p":"8078","l":"russian","d":"https://url03.ctfile.com/f/64369603-1509338962-857096?p=8078"},{"n":"16688、_russian_Повесть о футболе_Старостин Андрей Петрович_.fb2__pilimi-zlib-0-119999","i":"fb2","s":303207,"p":"8078","l":"russian","d":"https://url03.ctfile.com/f/64369603-1509338974-029d95?p=8078"},{"n":"16689、_russian_Флагман футбола_Старостин Андрей Петрович_.fb2__pilimi-zlib-0-119999","i":"fb2","s":247461,"p":"8078","l":"russian","d":"https://url03.ctfile.com/f/64369603-1509338986-c437b1?p=8078"}]