[{"n":"105893、_russian_Медовый месяц Золушки_Полонский Георгий__.fb2__pilimi-zlib-120000-419999-1","i":"fb2","s":19602,"p":"8078","l":"russian","d":"https://url03.ctfile.com/f/64369603-1512282388-7904ff?p=8078"},{"n":"105893、_russian_Танец демона_Зимина Светлана__.fb2__pilimi-zlib-120000-419999-1","i":"fb2","s":108139,"p":"8078","l":"russian","d":"https://url03.ctfile.com/f/64369603-1512282397-b8349d?p=8078"},{"n":"105894、_russian_Невеста Демона_Жданова Светлана__.fb2__pilimi-zlib-120000-419999-1","i":"fb2","s":384761,"p":"8078","l":"russian","d":"https://url03.ctfile.com/f/64369603-1512282406-306ee8?p=8078"},{"n":"105894、_russian_Словарь морских терминов встречающихся в рассказах_Станюкович Константин Михайлович__.fb2__pilimi-zlib-120000-419999-1","i":"fb2","s":20691,"p":"8078","l":"russian","d":"https://url03.ctfile.com/f/64369603-1512282415-d92194?p=8078"},{"n":"105895、_russian_Словарь морских терминов встречающихся в рассказах (2)_Станюкович Константин Михайлович__.fb2__pilimi-zlib-120000-419999-1","i":"fb2","s":20461,"p":"8078","l":"russian","d":"https://url03.ctfile.com/f/64369603-1512282427-ad0693?p=8078"},{"n":"105895、_russian_Эртан_Середа Светлана Викторовна__.fb2__pilimi-zlib-120000-419999-1","i":"fb2","s":18157,"p":"8078","l":"russian","d":"https://url03.ctfile.com/f/64369603-1512282436-80a83e?p=8078"},{"n":"105896、_russian_Словарь морских терминов встречающихся в рассказах_Станюкович Константин Михайлович__.fb2__pilimi-zlib-120000-419999-1","i":"fb2","s":22081,"p":"8078","l":"russian","d":"https://url03.ctfile.com/f/64369603-1512282442-7e40ed?p=8078"},{"n":"105896、_russian_Эртан_Середа Светлана Викторовна__.fb2__pilimi-zlib-120000-419999-1","i":"fb2","s":73356,"p":"8078","l":"russian","d":"https://url03.ctfile.com/f/64369603-1512282451-5cf265?p=8078"},{"n":"105897、_russian_Простой пациент_Билль-Белоцерковский Владимир Наумович__.fb2__pilimi-zlib-120000-419999-1","i":"fb2","s":35384,"p":"8078","l":"russian","d":"https://url03.ctfile.com/f/64369603-1512282457-df3d20?p=8078"},{"n":"105897、_russian_Шутка_Станюкович Константин Михайлович__.fb2__pilimi-zlib-120000-419999-1","i":"fb2","s":12955,"p":"8078","l":"russian","d":"https://url03.ctfile.com/f/64369603-1512282469-575c05?p=8078"},{"n":"105898、_russian_LoveLess. Повесть о ненастоящей женщине_Вебер Светлана__.fb2__pilimi-zlib-120000-419999-1","i":"fb2","s":18534,"p":"8078","l":"russian","d":"https://url03.ctfile.com/f/64369603-1512282475-13e904?p=8078"},{"n":"105898、_russian_Севастопольский мальчик_Станюкович Константин Михайлович__.fb2__pilimi-zlib-120000-419999-1","i":"fb2","s":21189,"p":"8078","l":"russian","d":"https://url03.ctfile.com/f/64369603-1512282481-a5f658?p=8078"},{"n":"105899、_russian_Массаж при заболеваниях опорно-двигательного аппарата_Устелимова Светлана__.fb2__pilimi-zlib-120000-419999-1","i":"fb2","s":10002,"p":"8078","l":"russian","d":"https://url03.ctfile.com/f/64369603-1512282484-6e52b6?p=8078"},{"n":"105899、_russian_Серж Птичкин_Станюкович Константин Михайлович__.fb2__pilimi-zlib-120000-419999-1","i":"fb2","s":22144,"p":"8078","l":"russian","d":"https://url03.ctfile.com/f/64369603-1512282493-9cf8c4?p=8078"},{"n":"10589、_russian_Златой век Екатерины II_Башилов Борис__.fb2__pilimi-zlib-120000-419999-1","i":"fb2","s":1004502,"p":"8078","l":"russian","d":"https://url03.ctfile.com/f/64369603-1512282499-4aad03?p=8078"},{"n":"105900、_russian_Массаж при гипертонии и гипотонии_Устелимова Светлана__.fb2__pilimi-zlib-120000-419999-1","i":"fb2","s":218778,"p":"8078","l":"russian","d":"https://url03.ctfile.com/f/64369603-1512282505-66b112?p=8078"},{"n":"105900、_russian_Рождественская ночь_Станюкович Константин Михайлович__.fb2__pilimi-zlib-120000-419999-1","i":"fb2","s":20436,"p":"8078","l":"russian","d":"https://url03.ctfile.com/f/64369603-1512282508-a3904a?p=8078"},{"n":"105901、_russian_Над пропастью во лжи_Успенская Светлана__.fb2__pilimi-zlib-120000-419999-1","i":"fb2","s":117657,"p":"8078","l":"russian","d":"https://url03.ctfile.com/f/64369603-1512282514-b989fd?p=8078"},{"n":"105901、_russian_Решение_Станюкович Константин Михайлович__.fb2__pilimi-zlib-120000-419999-1","i":"fb2","s":19803,"p":"8078","l":"russian","d":"https://url03.ctfile.com/f/64369603-1512282517-3a5bcd?p=8078"},{"n":"105902、_russian_Кодекс чести вампира_Сухомизская Светлана__.fb2__pilimi-zlib-120000-419999-1","i":"fb2","s":319914,"p":"8078","l":"russian","d":"https://url03.ctfile.com/f/64369603-1512282520-26ba25?p=8078"}]