{"bet团成员邪恶角度饭":"QS8AAA==","liore团肉色紧身衣邪恶角度饭拍视":"nyoAAA==","p高":"pxMAAA==","rhythm":"7ToAAA==","之美的全球":"jUAAAA==","佳莹金":"yDwAAA==","典红歌":"owAAAA8mAADBPAAA","卫视年":"UjQAAA==","品纯音":"vCoAABA3AADtOgAAMkAAAOhAAABzRAAA","唯美必":"qicAAA==","嗨现场":"fxUAAA==","在心间":"PEIAAA==","声d":"WxUAAOEgAAA=","声在倾":"hEkAAA==","大好处":"YDQAAA==","女之歌":"kB0AAA==","律悦耳清脆":"1SYAAA==","怡人养":"VE0AAA==","想音乐":"mjYAAA==","我们相":"6ikAAA==","搭错车":"UEEAAAAtAAA=","旋律深":"90UAAA==","曲只应":"0TwAAPZFAAA=","望星空":"jS4AAE4vAAAhQAAArUIAALNEAABvAAAAxB8AAA==","歌唱给":"dQAAAGQyAAA=","歌女之":"kB0AAA==","然好想":"8UAAAA==","现代钢":"+EUAAA==","琴dj经典歌曲12首联奏":"UTQAAA==","生奇妙与惊":"dT8AAA==","甸景色":"Xi8AAA==","留住岁月的":"0y0AAA==","白娘子":"ixoAAIwaAACNGgAAjhoAAA==","的人心":"CyEAAA==","的吉他金曲":"V0EAAA==","的旋律动感的节":"zCMAALCqAAA=","直击心":"S0EAAEZIAAA=","着喜庆和不":"rTsAAA==","知之地":"xEcAAA==","神曲下":"OjMAANU3AABRPgAA","秘园经":"PjsAAA==","空之城":"rzEAAEs2AACUZQAA","绵情依":"IjoAAA==","美腿芳":"P0oAAA==","花落雨":"UC8AAA==","血沸腾":"/SwAAA==","越南美女夜店蹦迪狂嗨现场":"fxUAAA==","身体和":"6TgAAA==","边疆泉":"qD4AAA==","金曲纯":"Rz4AAA==","金花惊艳瞬":"LDMAAA==","问月亮":"rioAAA==","音乐一":"WEEAAA==","音乐推":"SSwAAA==","音效极品电":"xy0AAA==","风低音":"CiEAAA==","高天上":"ExsAAA=="}