{"58f4eb2a7aa4fbeffba8c119ef58ffc2":"W3MMAA==","авшарян":"qaUPAA==","ажурные":"4kgMALzlDQA=","алтьери":"bjAOAA==","арахнея":"7lQNAA==","артания":"xr0PAA==","бертьен":"IosMACOLDAA=","брудершафт":"IukPAJHpDwDr6g8A/c4PAETpDwB76Q8AnekPAPbqDwAu6Q8AOekPAPYLEADdCxAAnM8PAIbpDwDf6g8A","брухнов":"53APAA==","булкаты":"c38PAA==","бутылка":"olAPADJSDwAJpw8A47APAFvgDwBCOgwAkMwNAGpADgA=","ведущая":"TeAPAOVRDwA=","взывают":"B18MAAmhDQA=","губайловский":"KToMALRSDwCyjA8A","дивногорцева":"h0oPAA==","дочурка":"YtINAA==","дурачок":"eowPAI9oDADzHg4A","дурочка":"oQEOAA==","катышев":"4DwOAA==","коло":"36wPAJOzDwBNDhAA","кредитование":"CjwOAA==","курваль":"+LoPAA==","ломм":"/rMPAMBIDAAIqgwA+CwOAPksDgC3cw8A","марышев":"mokPAA==","меркури":"Iq0MAIyiDwA=","монк":"1kgMAGjxDQCqRg8Au1APAMMKEAA=","научите":"kZkMAJa/DQAkCxAA","неархос":"1lQNABkPEADRVA0A0lQNANRUDQDVVA0A","незабываемая":"qloNAHVODwA=","непокоренных":"aU0PAA==","нерешительности":"bccPAA==","окол":"bhYQAA==","онассис":"Q6UPAA==","острове":"yO4NAPWwDwAXOgwAamwMACF1DAAmkw0AWvwNAJ0EDgBgSg8AyYQMAG8FDgBlag8AG9wPAObnDwCCbgwATgUOAOKBDwBo5A8A","партыка":"y9QPABfVDwDH1Q8AqtcPAM7XDwA=","паучиха":"ZeMNAN7kDwA=","перекур":"0RkOAA==","перерыв":"b/YPAA==","пнин":"i3cPAAmYDwDpOwwAaWsPAD90DwDLdg8A","попе":"wtsPAA==","поттера":"KAoQAA==","предлагаемые":"vjgOAA==","предтеч":"NB8OAGkfDgBrHw4AbB8OAOnxDwA=","разоблачение":"MjsOAGVDDwA=","рванець":"ThYQAA==","россией":"YjoOABhBDgC7nA8AK54PALVTDQAaOg4A","свисток":"ydMPADEVEAA=","скобарь":"2IsPAA==","сникерс":"kVMPAA==","сталину":"0sUPAP45DgCCoA8A","станции":"c7sPAERRDQCnVQ8AgfoPAEU5DABnXQwApbgNAL/9DQC3Hg4AjFUPAA7tDwDuJAwAQ1ENAL79DQCJHg4AUlcPAA==","стефени":"XO4PAA==","стриано":"SdkPAA==","суриков":"9LoNAPW6DQA=","суханов":"N6sPACscEACdqwwA","сушкова":"qxMOAA==","тайлеры":"eb0PABW9DwA=","таунсли":"i9gPAA==","терехин":"cl0PAA==","тупапау":"VhMMAEGiDQA=","ужасная":"rXoMAEnnDwA=","уилфрид":"sjcMANpaDwA=","уинтерз":"xFgMAIVyDABi8Q0AbvENAFZQDwDCWAwAw1gMAIRyDADe8Q0AiDkOAIk5DgCLOQ4AsfsPAA==","чемерис":"dgEQAA==","чудские":"UMoPAA==","ширяева":"LnENAI83DgAtcQ0A","эгрегор":"fv8NAA==","эдуардо":"GXINALlIDwDYxw8A8MwPAJ/NDwC5RQ0A78ANAObMDwDnzA8A","экстазе":"QnkPAA==","юденрат":"DrwPAA==","社":"2PMKACPHCgDW8woA","群":"I8cKAA=="}