[{"n":"书籍_【网络TXT电子书合集】-网上最全的电子书合集_中文字母索引-A_暗色之痛_再痕中文.txt","i":"txt","s":124634,"p":"1411","l":"chinese","d":"https://url05.ctfile.com/f/64714105-1518101602-12eae1?p=1411"},{"n":"书籍_【网络TXT电子书合集】-网上最全的电子书合集_中文字母索引-A_暗翼雪心_再痕中文.txt","i":"txt","s":181304,"p":"1411","l":"chinese","d":"https://url05.ctfile.com/f/64714105-1518101596-ee8220?p=1411"},{"n":"书籍_【网络TXT电子书合集】-网上最全的电子书合集_中文字母索引-A_暗红（我是“卖的”，咋啦！）_再痕中文.txt","i":"txt","s":302130,"p":"1411","l":"chinese","d":"https://url05.ctfile.com/f/64714105-1518101590-23f119?p=1411"},{"n":"书籍_【网络TXT电子书合集】-网上最全的电子书合集_中文字母索引-A_暗紫夙_再痕中文.txt","i":"txt","s":491499,"p":"1411","l":"chinese","d":"https://url05.ctfile.com/f/64714105-1518101578-8fe3a6?p=1411"},{"n":"书籍_【网络TXT电子书合集】-网上最全的电子书合集_中文字母索引-A_暗紫_再痕中文.txt","i":"txt","s":160668,"p":"1411","l":"chinese","d":"https://url05.ctfile.com/f/64714105-1518101572-6dff28?p=1411"},{"n":"书籍_【网络TXT电子书合集】-网上最全的电子书合集_中文字母索引-A_暗算_再痕中文.txt","i":"txt","s":169824,"p":"1411","l":"chinese","d":"https://url05.ctfile.com/f/64714105-1518101560-438ed9?p=1411"},{"n":"书籍_【网络TXT电子书合集】-网上最全的电子书合集_中文字母索引-A_暗盒_再痕中文.txt","i":"txt","s":1165,"p":"1411","l":"chinese","d":"https://url05.ctfile.com/f/64714105-1518101551-129044?p=1411"},{"n":"书籍_【网络TXT电子书合集】-网上最全的电子书合集_中文字母索引-A_暗灵法医_再痕中文.txt","i":"txt","s":1663277,"p":"1411","l":"chinese","d":"https://url05.ctfile.com/f/64714105-1518101545-4e8e70?p=1411"},{"n":"书籍_【网络TXT电子书合集】-网上最全的电子书合集_中文字母索引-A_暗淡_再痕中文.txt","i":"txt","s":283742,"p":"1411","l":"chinese","d":"https://url05.ctfile.com/f/64714105-1518101539-3dbb00?p=1411"},{"n":"书籍_【网络TXT电子书合集】-网上最全的电子书合集_中文字母索引-A_暗梦天堂_再痕中文.txt","i":"txt","s":834722,"p":"1411","l":"chinese","d":"https://url05.ctfile.com/f/64714105-1518101533-159e97?p=1411"},{"n":"书籍_【网络TXT电子书合集】-网上最全的电子书合集_中文字母索引-A_暗杀_再痕中文.txt","i":"txt","s":111911,"p":"1411","l":"chinese","d":"https://url05.ctfile.com/f/64714105-1518101524-4f87b7?p=1411"},{"n":"书籍_武侠小说合集_五大家武侠小说合集_温瑞安武侠小说全集整合版_温瑞安武侠小说全集_神州奇侠系列_方歌吟_逍遥游.txt","i":"txt","s":177612,"p":"1411","l":"chinese","d":"https://url05.ctfile.com/f/64714105-1517752411-d8473f?p=1411"},{"n":"书籍_武侠小说合集_五大家武侠小说合集_温瑞安武侠小说全集整合版_温瑞安武侠小说全集_神州奇侠系列_方歌吟_大宗师.txt","i":"txt","s":313059,"p":"1411","l":"chinese","d":"https://url05.ctfile.com/f/64714105-1517752408-d21b9f?p=1411"},{"n":"书籍_武侠小说合集_五大家武侠小说合集_温瑞安武侠小说全集整合版_温瑞安武侠小说全集_神州奇侠系列_方歌吟_人世间.txt","i":"txt","s":265862,"p":"1411","l":"chinese","d":"https://url05.ctfile.com/f/64714105-1517752402-55a9d8?p=1411"},{"n":"书籍_武侠小说合集_五大家武侠小说合集_温瑞安武侠小说全集整合版_温瑞安武侠小说全集_神州奇侠系列_方歌吟_养生主.txt","i":"txt","s":227332,"p":"1411","l":"chinese","d":"https://url05.ctfile.com/f/64714105-1517752405-191083?p=1411"},{"n":"书籍_武侠小说合集_五大家武侠小说合集_温瑞安武侠小说全集整合版_温瑞安武侠小说全集_神州奇侠系列_正传_08天下有雪.txt","i":"txt","s":257650,"p":"1411","l":"chinese","d":"https://url05.ctfile.com/f/64714105-1517752435-48d520?p=1411"},{"n":"书籍_武侠小说合集_五大家武侠小说合集_温瑞安武侠小说全集整合版_温瑞安武侠小说全集_神州奇侠系列_正传_07寂寞高手.txt","i":"txt","s":244821,"p":"1411","l":"chinese","d":"https://url05.ctfile.com/f/64714105-1517752432-e60571?p=1411"},{"n":"书籍_武侠小说合集_五大家武侠小说合集_温瑞安武侠小说全集整合版_温瑞安武侠小说全集_神州奇侠系列_正传_05英雄好汉.txt","i":"txt","s":257910,"p":"1411","l":"chinese","d":"https://url05.ctfile.com/f/64714105-1517752426-e155e8?p=1411"},{"n":"书籍_武侠小说合集_五大家武侠小说合集_温瑞安武侠小说全集整合版_温瑞安武侠小说全集_神州奇侠系列_正传_06神州无敌.txt","i":"txt","s":182611,"p":"1411","l":"chinese","d":"https://url05.ctfile.com/f/64714105-1517752429-36222a?p=1411"},{"n":"书籍_武侠小说合集_五大家武侠小说合集_温瑞安武侠小说全集整合版_温瑞安武侠小说全集_神州奇侠系列_正传_04闯荡江湖.txt","i":"txt","s":216725,"p":"1411","l":"chinese","d":"https://url05.ctfile.com/f/64714105-1517752423-0ebe80?p=1411"}]