[{"n":"书籍_《亚马逊原版电子书》7000本_《亚马逊原版电子书》序号4501-5000 共500本 本本好书 价值上万[azw3]_A04709. 大诱拐【推理小说 文春推理小说】.B09XM9DR3D.azw3","i":"azw3","s":548645,"p":"1411","l":"chinese","d":"https://url05.ctfile.com/f/64714105-1518068890-56cb77?p=1411"},{"n":"书籍_《亚马逊原版电子书》7000本_《亚马逊原版电子书》序号4501-5000 共500本 本本好书 价值上万[azw3]_A04708. 大诱拐【第32届日本推理作家协会奖、2013年东西推理BEST100第7位，仅次于《占星术杀人魔法》，力压《嫌疑人X的献身》，日本幽默推理先驱天藤真热门大作，笑点密集 温情治愈 热血沸腾！】.B09XM9DR3D.azw3","i":"azw3","s":540941,"p":"1411","l":"chinese","d":"https://url05.ctfile.com/f/64714105-1518068878-cc11e8?p=1411"},{"n":"书籍_《亚马逊原版电子书》7000本_《亚马逊原版电子书》序号4501-5000 共500本 本本好书 价值上万[azw3]_A04707. 大英图书馆物种艺术史【世界文明的诺亚方舟，荡气回肠的自然史诗。】.B0B12FBRQT.azw3","i":"azw3","s":30644544,"p":"1411","l":"chinese","d":"https://url05.ctfile.com/f/64714105-1518068875-16437e?p=1411"},{"n":"书籍_《亚马逊原版电子书》7000本_《亚马逊原版电子书》序号4501-5000 共500本 本本好书 价值上万[azw3]_A04706. 大英图书馆·侦探小说黄金时代经典作品集(第一辑)(套装共8册)：比逻辑推理更复杂的是人心，侦探小说爱好者不容错过之作.B08DFF68KB.azw3","i":"azw3","s":3637915,"p":"1411","l":"chinese","d":"https://url05.ctfile.com/f/64714105-1518068863-b323ad?p=1411"},{"n":"书籍_《亚马逊原版电子书》7000本_《亚马逊原版电子书》序号4501-5000 共500本 本本好书 价值上万[azw3]_A04705. 大英图书馆·侦探小说黄金时代经典作品集(第二辑)(套装共6册).B08LCZJGHC.azw3","i":"azw3","s":2548547,"p":"1411","l":"chinese","d":"https://url05.ctfile.com/f/64714105-1518068854-c3b8a4?p=1411"},{"n":"书籍_《亚马逊原版电子书》7000本_《亚马逊原版电子书》序号4501-5000 共500本 本本好书 价值上万[azw3]_A04704. 大英经典博物学（套装5册）（来自伦敦的经典博物学，中西合璧，硬核创作团队。超有趣的动物博物馆见证实录。感受地球上不同的脉动！）.B0895R6GDK.azw3","i":"azw3","s":49934193,"p":"1411","l":"chinese","d":"https://url05.ctfile.com/f/64714105-1518068848-d56978?p=1411"},{"n":"书籍_《亚马逊原版电子书》7000本_《亚马逊原版电子书》序号4501-5000 共500本 本本好书 价值上万[azw3]_A04703. 大英帝国与第一次世界大战.B07RVHMRS2.azw3","i":"azw3","s":8624969,"p":"1411","l":"chinese","d":"https://url05.ctfile.com/f/64714105-1518068842-335d44?p=1411"},{"n":"书籍_《亚马逊原版电子书》7000本_《亚马逊原版电子书》序号4501-5000 共500本 本本好书 价值上万[azw3]_A04702. 大英帝国简史（华文全球史）.B09SPNCH8S.azw3","i":"azw3","s":33609998,"p":"1411","l":"chinese","d":"https://url05.ctfile.com/f/64714105-1518068833-03e307?p=1411"},{"n":"书籍_《亚马逊原版电子书》7000本_《亚马逊原版电子书》序号4501-5000 共500本 本本好书 价值上万[azw3]_A04701. 大英帝国的崛起与衰落：震撼人心的大英帝国全历史，北大博雅讲席教授钱乘旦倾情推荐！.B07KXN1C9B.azw3","i":"azw3","s":4808282,"p":"1411","l":"chinese","d":"https://url05.ctfile.com/f/64714105-1518068824-a32b64?p=1411"},{"n":"书籍_《亚马逊原版电子书》7000本_《亚马逊原版电子书》序号6001-6500 共500本 本本好书 价值上万[azw3]_A06300. 梵蒂冈地窖 (纪德作品系列).B00SIO00VY.azw3","i":"azw3","s":926356,"p":"1411","l":"chinese","d":"https://url05.ctfile.com/f/64714105-1518074248-3fdee9?p=1411"},{"n":"书籍_《亚马逊原版电子书》7000本_《亚马逊原版电子书》序号6001-6500 共500本 本本好书 价值上万[azw3]_A06299. 梵澄译丛 云使之歌.B0BTSXHSTX.azw3","i":"azw3","s":195206,"p":"1411","l":"chinese","d":"https://url05.ctfile.com/f/64714105-1518074245-3fd0ab?p=1411"},{"n":"书籍_《亚马逊原版电子书》7000本_《亚马逊原版电子书》序号6001-6500 共500本 本本好书 价值上万[azw3]_A06298. 贩卖时光78天.B01NBVY96S.azw3","i":"azw3","s":421357,"p":"1411","l":"chinese","d":"https://url05.ctfile.com/f/64714105-1518074239-7ba6b0?p=1411"},{"n":"书籍_《亚马逊原版电子书》7000本_《亚马逊原版电子书》序号6001-6500 共500本 本本好书 价值上万[azw3]_A06297. 范稳作品集（全8册，豆瓣8.7分佳作，入选“新中国70年70部长篇小说典藏”，入围第七届茅盾文学奖终评作品，中国的《百年孤独》，范稳作品合集）.B09SPY1LLR.azw3","i":"azw3","s":41350539,"p":"1411","l":"chinese","d":"https://url05.ctfile.com/f/64714105-1518074236-410533?p=1411"},{"n":"书籍_《亚马逊原版电子书》7000本_《亚马逊原版电子书》序号6001-6500 共500本 本本好书 价值上万[azw3]_A06296. 范思哲香水 (阿福短篇悬念故事集).B0147YAQIU.azw3","i":"azw3","s":523204,"p":"1411","l":"chinese","d":"https://url05.ctfile.com/f/64714105-1518074233-e31df5?p=1411"},{"n":"书籍_《亚马逊原版电子书》7000本_《亚马逊原版电子书》序号6001-6500 共500本 本本好书 价值上万[azw3]_A06295. 泛神论要义 (汉译世界学术名著丛书).B00P2KOS88.azw3","i":"azw3","s":370598,"p":"1411","l":"chinese","d":"https://url05.ctfile.com/f/64714105-1518074230-949186?p=1411"},{"n":"书籍_《亚马逊原版电子书》7000本_《亚马逊原版电子书》序号6001-6500 共500本 本本好书 价值上万[azw3]_A06294. 泛函分析讲义(上).B00826D1X2.azw3","i":"azw3","s":7926708,"p":"1411","l":"chinese","d":"https://url05.ctfile.com/f/64714105-1518074227-5fba7a?p=1411"},{"n":"书籍_《亚马逊原版电子书》7000本_《亚马逊原版电子书》序号6001-6500 共500本 本本好书 价值上万[azw3]_A06293. 饭太稀个人绘本画集合辑（套装共3册）【知名人气插画师饭太稀绘本画集合集：《谢谢招待》《一个人》《不只一个人》，站酷网总编、LOFTER绘画频道负责人专文推荐，温暖时光不一定需要另一个人的陪伴，一个人并不意味着独立生活，何不来一场与自己同行之旅？】（漫友文化出品）.B08M9TLCM5.azw3","i":"azw3","s":46483584,"p":"1411","l":"chinese","d":"https://url05.ctfile.com/f/64714105-1518074224-3bd083?p=1411"},{"n":"书籍_《亚马逊原版电子书》7000本_《亚马逊原版电子书》序号6001-6500 共500本 本本好书 价值上万[azw3]_A06292. 饭否.B00F2AMSM6.azw3","i":"azw3","s":332301,"p":"1411","l":"chinese","d":"https://url05.ctfile.com/f/64714105-1518074218-80870b?p=1411"},{"n":"书籍_《亚马逊原版电子书》7000本_《亚马逊原版电子书》序号6001-6500 共500本 本本好书 价值上万[azw3]_A06291. 犯罪心理学.B0BHWBTF1Q.azw3","i":"azw3","s":2271091,"p":"1411","l":"chinese","d":"https://url05.ctfile.com/f/64714105-1518074209-bd5484?p=1411"},{"n":"书籍_《亚马逊原版电子书》7000本_《亚马逊原版电子书》序号6001-6500 共500本 本本好书 价值上万[azw3]_A06290. 犯罪心理学 (21世纪法学规划教材).B00WM94Z9E.azw3","i":"azw3","s":607854,"p":"1411","l":"chinese","d":"https://url05.ctfile.com/f/64714105-1518074203-033881?p=1411"}]